full_add_sub/full_sub/full_sub.v
module full_subtractor(
    input a,           // Minuend
    input b,           // Subtrahend
    input b_in,        // Borrow input
    output difference, // Difference output
    output b_out       // Borrow output
);

    assign difference = a ^ b ^ b_in;
    assign b_out = (~a & b) | ((~(a ^ b)) & b_in);

endmodule

full_add_sub/full_sub/full_sub_tb.v

module full_subtractor_tb;

  // Parameters

  //Ports
  reg a;
  reg b;
  reg b_in;
  wire difference;
  wire b_out;

  full_subtractor  full_subtractor_inst (
    .a(a),
    .b(b),
    .b_in(b_in),
    .difference(difference),
    .b_out(b_out)
  );
    initial begin
        // Waveform Dumping
        $dumpfile("full_subtractor_waves.vcd");
        $dumpvars(0, full_subtractor_tb);

        // Test Cases
        a = 0; b = 0; b_in = 0; #10;
        a = 0; b = 0; b_in = 1; #10;
        a = 0; b = 1; b_in = 0; #10;
        a = 0; b = 1; b_in = 1; #10;
        a = 1; b = 0; b_in = 0; #10;
        a = 1; b = 0; b_in = 1; #10;
        a = 1; b = 1; b_in = 0; #10;
        a = 1; b = 1; b_in = 1; #10;

        $finish; // End simulation
    end
//always #5  clk = ! clk ;

endmodule

full_add_sub/full_sub/full_subtractor_waves.vcd
$date
	Tue Feb 10 20:26:14 2026
$end
$version
	Icarus Verilog
$end
$timescale
	1s
$end
$scope module full_subtractor_tb $end
$var wire 1 ! difference $end
$var wire 1 " b_out $end
$var reg 1 # a $end
$var reg 1 $ b $end
$var reg 1 % b_in $end
$scope module full_subtractor_inst $end
$var wire 1 # a $end
$var wire 1 $ b $end
$var wire 1 % b_in $end
$var wire 1 " b_out $end
$var wire 1 ! difference $end
$upscope $end
$upscope $end
$enddefinitions $end
#0
$dumpvars
0%
0$
0#
0"
0!
$end
#10
1"
1!
1%
#20
0%
1$
#30
0!
1%
#40
0"
1!
0%
0$
1#
#50
0!
1%
#60
0%
1$
#70
1"
1!
1%
