flip_flop/flip_flop.v
// D Flip-Flop with Asynchronous Reset
module d_flip_flop (
    input  clk,       // Clock signal
    input  rst,       // Asynchronous reset (active-high)
    input  d,         // Data input
    output reg q,     // Output
    output     q_bar  // Complementary output
);

    assign q_bar = ~q;

    always @(posedge clk or posedge rst) begin
        if (rst)
            q <= 1'b0;
        else
            q <= d;
    end

endmodule

flip_flop/flip_flop_tb.v
`timescale 1ns / 1ps

module flip_flop_tb;

    // Declarations
    reg  clk;
    reg  rst;
    reg  d;
    wire q;
    wire q_bar;

    // Instantiate DUT
    d_flip_flop uut (
        .clk(clk),
        .rst(rst),
        .d(d),
        .q(q),
        .q_bar(q_bar)
    );

    // Clock generation: 10ns period (5ns high, 5ns low)
    always #5 clk = ~clk;

    initial begin
        $dumpfile("flip_flop_waves.vcd");
        $dumpvars(0, flip_flop_tb);

        // Initialize
        clk = 0; rst = 1; d = 0;
        #12; // Hold reset for a bit
        $display("t=%0t | rst=%b d=%b | q=%b q_bar=%b", $time, rst, d, q, q_bar);

        // Release reset
        rst = 0;

        // Test: d=0 → q should stay 0
        d = 0; #10;
        $display("t=%0t | rst=%b d=%b | q=%b q_bar=%b", $time, rst, d, q, q_bar);

        // Test: d=1 → q should become 1 on next rising edge
        d = 1; #10;
        $display("t=%0t | rst=%b d=%b | q=%b q_bar=%b", $time, rst, d, q, q_bar);

        // Test: d=0 → q should become 0 on next rising edge
        d = 0; #10;
        $display("t=%0t | rst=%b d=%b | q=%b q_bar=%b", $time, rst, d, q, q_bar);

        // Test: d=1 again
        d = 1; #10;
        $display("t=%0t | rst=%b d=%b | q=%b q_bar=%b", $time, rst, d, q, q_bar);

        // Test: Assert reset while running
        rst = 1; #10;
        $display("t=%0t | rst=%b d=%b | q=%b q_bar=%b (reset asserted)", $time, rst, d, q, q_bar);

        rst = 0; d = 1; #10;
        $display("t=%0t | rst=%b d=%b | q=%b q_bar=%b (reset released)", $time, rst, d, q, q_bar);

        #20;
        $finish;
    end

endmodule

flip_flop/flip_flop_waves.vcd
$date
	Thu Apr  2 09:30:26 2026
$end
$version
	Icarus Verilog
$end
$timescale
	1ps
$end
$scope module flip_flop_tb $end
$var wire 1 ! q_bar $end
$var wire 1 " q $end
$var reg 1 # clk $end
$var reg 1 $ d $end
$var reg 1 % rst $end
$scope module uut $end
$var wire 1 # clk $end
$var wire 1 $ d $end
$var wire 1 ! q_bar $end
$var wire 1 % rst $end
$var reg 1 " q $end
$upscope $end
$upscope $end
$enddefinitions $end
$comment Show the parameter values. $end
$dumpall
$end
#0
$dumpvars
1%
0$
0#
0"
1!
$end
#5000
1#
#10000
0#
#12000
0%
#15000
1#
#20000
0#
#22000
1$
#25000
0!
1"
1#
#30000
0#
#32000
0$
#35000
1!
0"
1#
#40000
0#
#42000
1$
#45000
0!
1"
1#
#50000
0#
#52000
1!
0"
1%
#55000
1#
#60000
0#
#62000
0%
#65000
0!
1"
1#
