sipo_register/sipo_register.v
// 4-Bit Serial-In Parallel-Out (SIPO) Shift Register
module sipo_4bit (
    input  clk,                    // Clock signal
    input  rst,                    // Asynchronous reset (active-high)
    input  serial_in,              // Serial data input
    output reg [3:0] parallel_out  // 4-bit parallel output
);

    always @(posedge clk or posedge rst) begin
        if (rst)
            parallel_out <= 4'b0000;
        else
            parallel_out <= {parallel_out[2:0], serial_in};  // Shift left, new bit enters LSB
    end

endmodule

sipo_register/sipo_register_tb.v
`timescale 1ns / 1ps

module sipo_register_tb;

    // Declarations
    reg  clk;
    reg  rst;
    reg  serial_in;
    wire [3:0] parallel_out;

    // Instantiate DUT
    sipo_4bit uut (
        .clk(clk),
        .rst(rst),
        .serial_in(serial_in),
        .parallel_out(parallel_out)
    );

    // Clock generation: 10ns period
    always #5 clk = ~clk;

    initial begin
        $dumpfile("sipo_register_waves.vcd");
        $dumpvars(0, sipo_register_tb);

        // Initialize
        clk = 0; rst = 1; serial_in = 0;
        #12;
        $display("t=%0t | rst=%b serial_in=%b | parallel_out=%b", $time, rst, serial_in, parallel_out);

        // Release reset
        rst = 0;

        // Shift in pattern: 1, 0, 1, 1 → expect parallel_out = 1011
        serial_in = 1; #10;
        $display("t=%0t | serial_in=%b | parallel_out=%b", $time, serial_in, parallel_out);

        serial_in = 0; #10;
        $display("t=%0t | serial_in=%b | parallel_out=%b", $time, serial_in, parallel_out);

        serial_in = 1; #10;
        $display("t=%0t | serial_in=%b | parallel_out=%b", $time, serial_in, parallel_out);

        serial_in = 1; #10;
        $display("t=%0t | serial_in=%b | parallel_out=%b", $time, serial_in, parallel_out);

        // Continue shifting: 0, 1 → observe shift behavior
        serial_in = 0; #10;
        $display("t=%0t | serial_in=%b | parallel_out=%b", $time, serial_in, parallel_out);

        serial_in = 1; #10;
        $display("t=%0t | serial_in=%b | parallel_out=%b", $time, serial_in, parallel_out);

        // Test reset mid-operation
        rst = 1; #10;
        $display("t=%0t | rst=%b | parallel_out=%b (reset asserted)", $time, rst, parallel_out);

        rst = 0; serial_in = 1; #10;
        $display("t=%0t | rst=%b serial_in=%b | parallel_out=%b (reset released)", $time, rst, serial_in, parallel_out);

        #20;
        $finish;
    end

endmodule

sipo_register/sipo_register_waves.vcd
$date
	Thu Apr  2 10:33:16 2026
$end
$version
	Icarus Verilog
$end
$timescale
	1ps
$end
$scope module sipo_register_tb $end
$var wire 4 ! parallel_out [3:0] $end
$var reg 1 " clk $end
$var reg 1 # rst $end
$var reg 1 $ serial_in $end
$scope module uut $end
$var wire 1 " clk $end
$var wire 1 # rst $end
$var wire 1 $ serial_in $end
$var reg 4 % parallel_out [3:0] $end
$upscope $end
$upscope $end
$enddefinitions $end
$comment Show the parameter values. $end
$dumpall
$end
#0
$dumpvars
b0 %
0$
1#
0"
b0 !
$end
#5000
1"
#10000
0"
#12000
1$
0#
#15000
b1 !
b1 %
1"
#20000
0"
#22000
0$
#25000
b10 !
b10 %
1"
#30000
0"
#32000
1$
#35000
b101 !
b101 %
1"
#40000
0"
#45000
b1011 !
b1011 %
1"
#50000
0"
#52000
0$
#55000
b110 !
b110 %
1"
#60000
0"
#62000
1$
#65000
b1101 !
b1101 %
1"
#70000
0"
#72000
b0 !
b0 %
1#
#75000
1"
#80000
0"
#82000
0#
#85000
b1 !
b1 %
1"
#90000
0"
#95000
b11 !
b11 %
1"
#100000
0"
#105000
b111 !
b111 %
1"
