priority_encoder/priority_encoder.v
// 8:3 Priority Encoder
// Higher-indexed input has higher priority
module priority_encoder_8to3 (
    input  [7:0] d,      // 8-bit input
    output reg [2:0] y,   // 3-bit encoded output
    output reg valid      // High when at least one input is active
);

    always @(*) begin
        if (d[7])      begin y = 3'd7; valid = 1'b1; end
        else if (d[6]) begin y = 3'd6; valid = 1'b1; end
        else if (d[5]) begin y = 3'd5; valid = 1'b1; end
        else if (d[4]) begin y = 3'd4; valid = 1'b1; end
        else if (d[3]) begin y = 3'd3; valid = 1'b1; end
        else if (d[2]) begin y = 3'd2; valid = 1'b1; end
        else if (d[1]) begin y = 3'd1; valid = 1'b1; end
        else if (d[0]) begin y = 3'd0; valid = 1'b1; end
        else           begin y = 3'd0; valid = 1'b0; end
    end

endmodule

priority_encoder/priority_encoder_tb.v
`timescale 1ns / 1ps

module priority_encoder_tb;

    // Declarations
    reg  [7:0] d;
    wire [2:0] y;
    wire valid;

    // Instantiate DUT
    priority_encoder_8to3 uut (
        .d(d),
        .y(y),
        .valid(valid)
    );

    initial begin
        $dumpfile("priority_encoder_waves.vcd");
        $dumpvars(0, priority_encoder_tb);

        // Test: No input active
        d = 8'b0000_0000; #10;
        $display("d=%b | y=%d valid=%b", d, y, valid);

        // Test: Single inputs
        d = 8'b0000_0001; #10;
        $display("d=%b | y=%d valid=%b", d, y, valid);

        d = 8'b0000_0100; #10;
        $display("d=%b | y=%d valid=%b", d, y, valid);

        d = 8'b1000_0000; #10;
        $display("d=%b | y=%d valid=%b", d, y, valid);

        // Test: Multiple inputs — highest priority wins
        d = 8'b0101_0010; #10;
        $display("d=%b | y=%d valid=%b", d, y, valid);

        d = 8'b1010_1010; #10;
        $display("d=%b | y=%d valid=%b", d, y, valid);

        d = 8'b0000_0110; #10;
        $display("d=%b | y=%d valid=%b", d, y, valid);

        d = 8'b1111_1111; #10;
        $display("d=%b | y=%d valid=%b", d, y, valid);

        $finish;
    end

endmodule

priority_encoder/priority_encoder_waves.vcd
$date
	Thu Apr  2 09:43:25 2026
$end
$version
	Icarus Verilog
$end
$timescale
	1ps
$end
$scope module priority_encoder_tb $end
$var wire 3 ! y [2:0] $end
$var wire 1 " valid $end
$var reg 8 # d [7:0] $end
$scope module uut $end
$var wire 8 $ d [7:0] $end
$var reg 1 " valid $end
$var reg 3 % y [2:0] $end
$upscope $end
$upscope $end
$enddefinitions $end
$comment Show the parameter values. $end
$dumpall
$end
#0
$dumpvars
b0 %
b0 $
b0 #
0"
b0 !
$end
#10000
1"
b1 #
b1 $
#20000
b10 !
b10 %
b100 #
b100 $
#30000
b111 !
b111 %
b10000000 #
b10000000 $
#40000
b110 !
b110 %
b1010010 #
b1010010 $
#50000
b111 !
b111 %
b10101010 #
b10101010 $
#60000
b10 !
b10 %
b110 #
b110 $
#70000
b111 !
b111 %
b11111111 #
b11111111 $
