mux4ex1/mux4.v
module mux4x1_dataflow (
    input [3:0] i,      // 4-bit input bus (i[0], i[1], i[2], i[3])
    input [1:0] s,      // 2-bit select line
    output y            // Scalar output
);

    // Index-select to infer a single 4:1 mux
    assign y = i[s];

endmodule

mux4ex1/mux4_tb.v

module mux4x1_dataflow_tb;

  // Ports
  reg [3:0] i;
  reg [1:0] s;
  wire y;

  mux4x1_dataflow  mux4x1_dataflow_inst (
    .i(i),
    .s(s),
    .y(y)
  );

//always #5  clk = ! clk ;
    integer si;
    initial begin
      // Waveform Dumping
      $dumpfile("mux4x1_waves.vcd");
      $dumpvars(0, mux4x1_dataflow_tb);

      // Test Cases
      i = 4'b0001;
      for (si = 0; si < 4; si = si + 1) begin
        s = si[1:0];
        #10;
      end

      i = 4'b1010;
      for (si = 0; si < 4; si = si + 1) begin
        s = si[1:0];
        #10;
      end

      i = 4'b1111;
      for (si = 0; si < 4; si = si + 1) begin
        s = si[1:0];
        #10;
      end

      $finish; // End simulation
    end

endmodule

mux4ex1/mux4x1_waves.vcd
$date
	Tue Feb 10 21:38:13 2026
$end
$version
	Icarus Verilog
$end
$timescale
	1s
$end
$scope module mux4x1_dataflow_tb $end
$var wire 1 ! y $end
$var reg 4 " i [3:0] $end
$var reg 2 # s [1:0] $end
$var integer 32 $ si [31:0] $end
$scope module mux4x1_dataflow_inst $end
$var wire 4 % i [3:0] $end
$var wire 2 & s [1:0] $end
$var wire 1 ! y $end
$upscope $end
$upscope $end
$enddefinitions $end
#0
$dumpvars
b0 &
b1 %
b0 $
b0 #
b1 "
1!
$end
#10
0!
b1 #
b1 &
b1 $
#20
b10 #
b10 &
b10 $
#30
b11 #
b11 &
b11 $
#40
b0 #
b0 &
0!
b1010 "
b1010 %
b0 $
#50
1!
b1 #
b1 &
b1 $
#60
0!
b10 #
b10 &
b10 $
#70
1!
b11 #
b11 &
b11 $
#80
b0 #
b0 &
b1111 "
b1111 %
b0 $
#90
b1 #
b1 &
b1 $
#100
b10 #
b10 &
b10 $
#110
b11 #
b11 &
b11 $
#120
b100 $
