d_flip_flop/d_flip_flop.v
// D Flip-Flop with Synchronous Reset
module d_flip_flop (
    input  clk,       // Clock signal
    input  rst,       // Synchronous reset (active-high)
    input  d,         // Data input
    output reg q,     // Output
    output     q_bar  // Complementary output
);

    assign q_bar = ~q;

    always @(posedge clk) begin
        if (rst)
            q <= 1'b0;
        else
            q <= d;
    end

endmodule

d_flip_flop/d_flip_flop_tb.v
`timescale 1ns / 1ps

module d_flip_flop_tb;

    // Declarations
    reg  clk;
    reg  rst;
    reg  d;
    wire q;
    wire q_bar;
    integer pass_count;
    integer fail_count;

    // Instantiate DUT
    d_flip_flop uut (
        .clk(clk),
        .rst(rst),
        .d(d),
        .q(q),
        .q_bar(q_bar)
    );

    // Clock generation: 10ns period
    always #5 clk = ~clk;

    task check_outputs;
        input exp_q;
        input exp_q_bar;
        input [255:0] test_name;
        begin
            if ((q !== exp_q) || (q_bar !== exp_q_bar)) begin
                fail_count = fail_count + 1;
                $display("FAIL | t=%0t | %0s | exp(q,q_bar)=(%b,%b) got=(%b,%b)",
                         $time, test_name, exp_q, exp_q_bar, q, q_bar);
            end else begin
                pass_count = pass_count + 1;
                $display("PASS | t=%0t | %0s | q=%b q_bar=%b",
                         $time, test_name, q, q_bar);
            end
        end
    endtask

    initial begin
        $dumpfile("d_flip_flop_waves.vcd");
        $dumpvars(0, d_flip_flop_tb);

        // Initialize
        clk = 1'b0;
        rst = 1'b1;
        d = 1'b0;
        pass_count = 0;
        fail_count = 0;

        // Hold synchronous reset for two rising edges
        repeat (2) @(posedge clk);
        #1;
        check_outputs(1'b0, 1'b1, "reset hold");

        // Release reset and apply edge-aligned test vectors
        rst = 1'b0;

        d = 1'b0;
        @(posedge clk);
        #1;
        check_outputs(1'b0, 1'b1, "d=0 capture");

        d = 1'b1;
        @(posedge clk);
        #1;
        check_outputs(1'b1, 1'b0, "d=1 capture");

        d = 1'b0;
        @(posedge clk);
        #1;
        check_outputs(1'b0, 1'b1, "d toggles to 0");

        d = 1'b1;
        @(posedge clk);
        #1;
        check_outputs(1'b1, 1'b0, "d toggles to 1");

        // Assert reset during operation (takes effect on clock edge)
        rst = 1'b1;
        d = 1'b1;
        @(posedge clk);
        #1;
        check_outputs(1'b0, 1'b1, "reset asserted in run");

        // Release reset and capture again
        rst = 1'b0;
        d = 1'b1;
        @(posedge clk);
        #1;
        check_outputs(1'b1, 1'b0, "post-reset capture");

        $display("SUMMARY | PASS=%0d FAIL=%0d", pass_count, fail_count);
        $finish;
    end

endmodule

d_flip_flop/d_flip_flop_waves.vcd
$date
	Fri Apr 24 08:06:37 2026
$end
$version
	Icarus Verilog
$end
$timescale
	1ps
$end
$scope module d_flip_flop_tb $end
$var wire 1 ! q_bar $end
$var wire 1 " q $end
$var reg 1 # clk $end
$var reg 1 $ d $end
$var reg 1 % rst $end
$var integer 32 & fail_count [31:0] $end
$var integer 32 ' pass_count [31:0] $end
$scope module uut $end
$var wire 1 # clk $end
$var wire 1 $ d $end
$var wire 1 ! q_bar $end
$var wire 1 % rst $end
$var reg 1 " q $end
$upscope $end
$scope task check_outputs $end
$var reg 1 ( exp_q $end
$var reg 1 ) exp_q_bar $end
$var reg 256 * test_name [255:0] $end
$upscope $end
$upscope $end
$enddefinitions $end
$comment Show the parameter values. $end
$dumpall
$end
#0
$dumpvars
bx *
x)
x(
b0 '
b0 &
1%
0$
0#
x"
x!
$end
#5000
1!
0"
1#
#10000
0#
#15000
1#
#16000
0%
b1 '
b1110010011001010111001101100101011101000010000001101000011011110110110001100100 *
1)
0(
#20000
0#
#25000
1#
#26000
1$
b10 '
b110010000111101001100000010000001100011011000010111000001110100011101010111001001100101 *
#30000
0#
#35000
0!
1"
1#
#36000
0$
b11 '
b110010000111101001100010010000001100011011000010111000001110100011101010111001001100101 *
0)
1(
#40000
0#
#45000
1!
0"
1#
#46000
1$
b100 '
b110010000100000011101000110111101100111011001110110110001100101011100110010000001110100011011110010000000110000 *
1)
0(
#50000
0#
#55000
0!
1"
1#
#56000
1%
b101 '
b110010000100000011101000110111101100111011001110110110001100101011100110010000001110100011011110010000000110001 *
0)
1(
#60000
0#
#65000
1!
0"
1#
#66000
0%
b110 '
b11100100110010101110011011001010111010000100000011000010111001101110011011001010111001001110100011001010110010000100000011010010110111000100000011100100111010101101110 *
1)
0(
#70000
0#
#75000
0!
1"
1#
#76000
b111 '
b11100000110111101110011011101000010110101110010011001010111001101100101011101000010000001100011011000010111000001110100011101010111001001100101 *
0)
1(
