sevensegment/sevensegment.v
// BCD to 7-Segment Decoder (Active-Low Outputs)
// Segments: seg[6:0] = {g, f, e, d, c, b, a}
module bcd_to_7seg (
    input  [3:0] bcd,      // 4-bit BCD input (0–9)
    output reg [6:0] seg   // 7-segment output (active-low)
);

    always @(*) begin
        case (bcd)
            4'd0: seg = 7'b100_0000;  // 0
            4'd1: seg = 7'b111_1001;  // 1
            4'd2: seg = 7'b010_0100;  // 2
            4'd3: seg = 7'b011_0000;  // 3
            4'd4: seg = 7'b001_1001;  // 4
            4'd5: seg = 7'b001_0010;  // 5
            4'd6: seg = 7'b000_0010;  // 6
            4'd7: seg = 7'b111_1000;  // 7
            4'd8: seg = 7'b000_0000;  // 8
            4'd9: seg = 7'b001_0000;  // 9
            default: seg = 7'b111_1111;  // Blank for invalid BCD
        endcase
    end

endmodule

sevensegment/sevensegment_tb.v
`timescale 1ns / 1ps

module sevensegment_tb;

    // Declarations
    reg  [3:0] bcd;
    wire [6:0] seg;

    // Instantiate DUT
    bcd_to_7seg uut (
        .bcd(bcd),
        .seg(seg)
    );

    integer i;

    initial begin
        $dumpfile("sevensegment_waves.vcd");
        $dumpvars(0, sevensegment_tb);

        bcd = 4'd0;

        // Sweep through all 16 possible inputs
        for (i = 0; i < 16; i = i + 1) begin
            bcd = i;
            #10;
            $display("BCD=%0d (4'b%b) | seg=%b", bcd, bcd, seg);
        end

        #10;
        $finish;
    end

endmodule

sevensegment/sevensegment_waves.vcd
$date
	Thu Apr  2 10:33:08 2026
$end
$version
	Icarus Verilog
$end
$timescale
	1ps
$end
$scope module sevensegment_tb $end
$var wire 7 ! seg [6:0] $end
$var reg 4 " bcd [3:0] $end
$var integer 32 # i [31:0] $end
$scope module uut $end
$var wire 4 $ bcd [3:0] $end
$var reg 7 % seg [6:0] $end
$upscope $end
$upscope $end
$enddefinitions $end
$comment Show the parameter values. $end
$dumpall
$end
#0
$dumpvars
b1000000 %
b0 $
b0 #
b0 "
b1000000 !
$end
#10000
b1111001 !
b1111001 %
b1 "
b1 $
b1 #
#20000
b100100 !
b100100 %
b10 "
b10 $
b10 #
#30000
b110000 !
b110000 %
b11 "
b11 $
b11 #
#40000
b11001 !
b11001 %
b100 "
b100 $
b100 #
#50000
b10010 !
b10010 %
b101 "
b101 $
b101 #
#60000
b10 !
b10 %
b110 "
b110 $
b110 #
#70000
b1111000 !
b1111000 %
b111 "
b111 $
b111 #
#80000
b0 !
b0 %
b1000 "
b1000 $
b1000 #
#90000
b10000 !
b10000 %
b1001 "
b1001 $
b1001 #
#100000
b1111111 !
b1111111 %
b1010 "
b1010 $
b1010 #
#110000
b1011 "
b1011 $
b1011 #
#120000
b1100 "
b1100 $
b1100 #
#130000
b1101 "
b1101 $
b1101 #
#140000
b1110 "
b1110 $
b1110 #
#150000
b1111 "
b1111 $
b1111 #
#160000
b10000 #
