full_add_sub/full_add/full_adder.v
module full_adder(
    input a,
    input b,
    input carry_in,
    output sum,
    output carry_out
);
    assign sum = a ^ b ^ carry_in;
    assign carry_out = (a & b) | (carry_in & (a ^ b));
endmodule

full_add_sub/full_add/full_adder_sub_tb.v

module full_adder_tb;

  // Parameters

  //Ports
  reg a;
  reg b;
  reg carry_in;
  wire sum;
  wire carry_out;

  full_adder  full_adder_inst (
    .a(a),
    .b(b),
    .carry_in(carry_in),
    .sum(sum),
    .carry_out(carry_out)
  );

//always #5  clk = ! clk ;
    initial begin
        // Waveform Dumping
        $dumpfile("full_adder_waves.vcd");
        $dumpvars(0, full_adder_tb);

        // Test Cases
        a = 0; b = 0; carry_in = 0; #10;
        a = 0; b = 0; carry_in = 1; #10;
        a = 0; b = 1; carry_in = 0; #10;
        a = 0; b = 1; carry_in = 1; #10;
        a = 1; b = 0; carry_in = 0; #10;
        a = 1; b = 0; carry_in = 1; #10;
        a = 1; b = 1; carry_in = 0; #10;
        a = 1; b = 1; carry_in = 1; #10;

        $finish; // End simulation
    end

endmodule

full_add_sub/full_add/full_adder_waves.vcd
$date
	Tue Feb 10 19:58:25 2026
$end
$version
	Icarus Verilog
$end
$timescale
	1s
$end
$scope module full_adder_tb $end
$var wire 1 ! sum $end
$var wire 1 " carry_out $end
$var reg 1 # a $end
$var reg 1 $ b $end
$var reg 1 % carry_in $end
$scope module full_adder_inst $end
$var wire 1 # a $end
$var wire 1 $ b $end
$var wire 1 % carry_in $end
$var wire 1 " carry_out $end
$var wire 1 ! sum $end
$upscope $end
$upscope $end
$enddefinitions $end
#0
$dumpvars
0%
0$
0#
0"
0!
$end
#10
1!
1%
#20
0%
1$
#30
1"
0!
1%
#40
0"
1!
0%
0$
1#
#50
1"
0!
1%
#60
0%
1$
#70
1!
1%
