pipo_register/pipo_register.v
// 4-bit PIPO (Parallel-In Parallel-Out) Register with Synchronous Load and Reset
module pipo_register (
    input        clk,       // Clock signal
    input        rst,       // Synchronous reset (active-high)
    input        load,      // Load enable (active-high)
    input  [3:0] d,         // Parallel data input
    output reg [3:0] q      // Parallel data output
);

    always @(posedge clk) begin
        if (rst)
            q <= 4'b0000;
        else if (load)
            q <= d;
    end

endmodule

pipo_register/pipo_register_tb.v
`timescale 1ns / 1ps

module pipo_register_tb;

    reg        clk;
    reg        rst;
    reg        load;
    reg  [3:0] d;
    wire [3:0] q;

    // Instantiate DUT
    pipo_register uut (
        .clk(clk),
        .rst(rst),
        .load(load),
        .d(d),
        .q(q)
    );

    // Clock generation: 10ns period
    always #5 clk = ~clk;

    initial begin
        $dumpfile("pipo_register_waves.vcd");
        $dumpvars(0, pipo_register_tb);

        // Initialize & reset
        clk = 0; rst = 1; load = 0; d = 4'b0000;
        #10;
        $display("t=%0t | rst=%b load=%b d=%b | q=%b (reset)", $time, rst, load, d, q);

        rst = 0;

        // Load data = 1010
        d = 4'b1010; load = 1; #10;
        $display("t=%0t | rst=%b load=%b d=%b | q=%b (load 1010)", $time, rst, load, d, q);

        // Hold (load=0, d changes but q unchanged)
        d = 4'b0101; load = 0; #10;
        $display("t=%0t | rst=%b load=%b d=%b | q=%b (hold)", $time, rst, load, d, q);

        // Load data = 1111
        d = 4'b1111; load = 1; #10;
        $display("t=%0t | rst=%b load=%b d=%b | q=%b (load 1111)", $time, rst, load, d, q);

        // Load data = 0110
        d = 4'b0110; load = 1; #10;
        $display("t=%0t | rst=%b load=%b d=%b | q=%b (load 0110)", $time, rst, load, d, q);

        // Reset while data loaded
        rst = 1; load = 0; #10;
        $display("t=%0t | rst=%b load=%b d=%b | q=%b (reset asserted)", $time, rst, load, d, q);

        rst = 0; d = 4'b1100; load = 1; #10;
        $display("t=%0t | rst=%b load=%b d=%b | q=%b (load after reset)", $time, rst, load, d, q);

        #20;
        $finish;
    end

endmodule

pipo_register/pipo_register_waves.vcd
$date
	Fri Apr 17 11:19:04 2026
$end
$version
	Icarus Verilog
$end
$timescale
	1ps
$end
$scope module pipo_register_tb $end
$var wire 4 ! q [3:0] $end
$var reg 1 " clk $end
$var reg 4 # d [3:0] $end
$var reg 1 $ load $end
$var reg 1 % rst $end
$scope module uut $end
$var wire 1 " clk $end
$var wire 4 & d [3:0] $end
$var wire 1 $ load $end
$var wire 1 % rst $end
$var reg 4 ' q [3:0] $end
$upscope $end
$upscope $end
$enddefinitions $end
$comment Show the parameter values. $end
$dumpall
$end
#0
$dumpvars
bx '
b0 &
1%
0$
b0 #
0"
bx !
$end
#5000
b0 !
b0 '
1"
#10000
0"
1$
b1010 #
b1010 &
0%
#15000
b1010 !
b1010 '
1"
#20000
0"
0$
b101 #
b101 &
#25000
1"
#30000
0"
1$
b1111 #
b1111 &
#35000
b1111 !
b1111 '
1"
#40000
0"
b110 #
b110 &
#45000
b110 !
b110 '
1"
#50000
0"
0$
1%
#55000
b0 !
b0 '
1"
#60000
0"
1$
b1100 #
b1100 &
0%
#65000
b1100 !
b1100 '
1"
