ripple_carry_adder/ripple_carry_adder.v
// Full Adder: single-bit building block for the ripple carry adder
module full_adder(
    input  A,
    input  B,
    input  Cin,
    output Sum,
    output Cout
);
    assign Sum  = A ^ B ^ Cin;
    assign Cout = (A & B) | (B & Cin) | (A & Cin);
endmodule

// Parameterized N-bit Ripple Carry Adder
// Default width is 4 bits; override with #(N) at instantiation time.
module ripple_carry_adder #(parameter N = 4)(
    input  [N-1:0] A,
    input  [N-1:0] B,
    input          Cin,
    output [N-1:0] Sum,
    output         Cout
);
    wire [N:0] carry;           // carry[0] = Cin, carry[N] = Cout
    assign carry[0] = Cin;

    genvar i;
    generate
        for (i = 0; i < N; i = i + 1) begin : fa_stage
            full_adder fa (
                .A   (A[i]),
                .B   (B[i]),
                .Cin (carry[i]),
                .Sum (Sum[i]),
                .Cout(carry[i+1])
            );
        end
    endgenerate

    assign Cout = carry[N];
endmodule

ripple_carry_adder/ripple_carry_adder_tb.v
`timescale 1ns/1ps

module ripple_carry_adder_tb;

    // ---- 4-bit instance ----
    parameter N4 = 4;
    reg  [N4-1:0] A4, B4;
    reg            Cin4;
    wire [N4-1:0] Sum4;
    wire           Cout4;

    ripple_carry_adder #(.N(N4)) uut4 (
        .A   (A4),
        .B   (B4),
        .Cin (Cin4),
        .Sum (Sum4),
        .Cout(Cout4)
    );

    // ---- 8-bit instance ----
    parameter N8 = 8;
    reg  [N8-1:0] A8, B8;
    reg            Cin8;
    wire [N8-1:0] Sum8;
    wire           Cout8;

    ripple_carry_adder #(.N(N8)) uut8 (
        .A   (A8),
        .B   (B8),
        .Cin (Cin8),
        .Sum (Sum8),
        .Cout(Cout8)
    );

    initial begin
        $dumpfile("ripple_carry_adder_waves.vcd");
        $dumpvars(0, ripple_carry_adder_tb);

        // ---- 4-bit tests ----
        $display("=== 4-bit Ripple Carry Adder ===");
        $display("A    B    Cin | Sum  Cout");

        // Simple addition
        A4 = 4'd2;  B4 = 4'd3;  Cin4 = 1'b0; #10;
        $display("%4d %4d  %b   | %4d  %b", A4, B4, Cin4, Sum4, Cout4);

        // Addition with carry-in
        A4 = 4'd5;  B4 = 4'd5;  Cin4 = 1'b1; #10;
        $display("%4d %4d  %b   | %4d  %b", A4, B4, Cin4, Sum4, Cout4);

        // Overflow (Cout asserted)
        A4 = 4'd15; B4 = 4'd1;  Cin4 = 1'b0; #10;
        $display("%4d %4d  %b   | %4d  %b", A4, B4, Cin4, Sum4, Cout4);

        // Max values with carry-in
        A4 = 4'hf;  B4 = 4'hf;  Cin4 = 1'b1; #10;
        $display("%4d %4d  %b   | %4d  %b", A4, B4, Cin4, Sum4, Cout4);

        // Zero addition
        A4 = 4'd0;  B4 = 4'd0;  Cin4 = 1'b0; #10;
        $display("%4d %4d  %b   | %4d  %b", A4, B4, Cin4, Sum4, Cout4);

        // ---- 8-bit tests ----
        $display("\n=== 8-bit Ripple Carry Adder ===");
        $display("A      B    Cin | Sum   Cout");

        // Simple addition
        A8 = 8'd100; B8 = 8'd55;  Cin8 = 1'b0; #10;
        $display("%6d %6d  %b   | %6d  %b", A8, B8, Cin8, Sum8, Cout8);

        // Addition with carry-in
        A8 = 8'd127; B8 = 8'd127; Cin8 = 1'b1; #10;
        $display("%6d %6d  %b   | %6d  %b", A8, B8, Cin8, Sum8, Cout8);

        // Overflow (Cout asserted)
        A8 = 8'd255; B8 = 8'd1;   Cin8 = 1'b0; #10;
        $display("%6d %6d  %b   | %6d  %b", A8, B8, Cin8, Sum8, Cout8);

        // Max values with carry-in
        A8 = 8'hff; B8 = 8'hff;   Cin8 = 1'b1; #10;
        $display("%6d %6d  %b   | %6d  %b", A8, B8, Cin8, Sum8, Cout8);

        $finish;
    end
endmodule

ripple_carry_adder/ripple_carry_adder_waves.vcd
$date
	Fri Apr 24 05:12:55 2026
$end
$version
	Icarus Verilog
$end
$timescale
	1ps
$end
$scope module ripple_carry_adder_tb $end
$var wire 8 ! Sum8 [7:0] $end
$var wire 4 " Sum4 [3:0] $end
$var wire 1 # Cout8 $end
$var wire 1 $ Cout4 $end
$var parameter 32 % N4 $end
$var parameter 32 & N8 $end
$var reg 4 ' A4 [3:0] $end
$var reg 8 ( A8 [7:0] $end
$var reg 4 ) B4 [3:0] $end
$var reg 8 * B8 [7:0] $end
$var reg 1 + Cin4 $end
$var reg 1 , Cin8 $end
$scope module uut4 $end
$var wire 4 - A [3:0] $end
$var wire 4 . B [3:0] $end
$var wire 1 + Cin $end
$var wire 5 / carry [4:0] $end
$var wire 4 0 Sum [3:0] $end
$var wire 1 $ Cout $end
$var parameter 32 1 N $end
$scope begin fa_stage[0] $end
$var parameter 2 2 i $end
$scope module fa $end
$var wire 1 3 A $end
$var wire 1 4 B $end
$var wire 1 5 Cin $end
$var wire 1 6 Cout $end
$var wire 1 7 Sum $end
$upscope $end
$upscope $end
$scope begin fa_stage[1] $end
$var parameter 2 8 i $end
$scope module fa $end
$var wire 1 9 A $end
$var wire 1 : B $end
$var wire 1 ; Cin $end
$var wire 1 < Cout $end
$var wire 1 = Sum $end
$upscope $end
$upscope $end
$scope begin fa_stage[2] $end
$var parameter 3 > i $end
$scope module fa $end
$var wire 1 ? A $end
$var wire 1 @ B $end
$var wire 1 A Cin $end
$var wire 1 B Cout $end
$var wire 1 C Sum $end
$upscope $end
$upscope $end
$scope begin fa_stage[3] $end
$var parameter 3 D i $end
$scope module fa $end
$var wire 1 E A $end
$var wire 1 F B $end
$var wire 1 G Cin $end
$var wire 1 H Cout $end
$var wire 1 I Sum $end
$upscope $end
$upscope $end
$upscope $end
$scope module uut8 $end
$var wire 8 J A [7:0] $end
$var wire 8 K B [7:0] $end
$var wire 1 , Cin $end
$var wire 9 L carry [8:0] $end
$var wire 8 M Sum [7:0] $end
$var wire 1 # Cout $end
$var parameter 32 N N $end
$scope begin fa_stage[0] $end
$var parameter 2 O i $end
$scope module fa $end
$var wire 1 P A $end
$var wire 1 Q B $end
$var wire 1 R Cin $end
$var wire 1 S Cout $end
$var wire 1 T Sum $end
$upscope $end
$upscope $end
$scope begin fa_stage[1] $end
$var parameter 2 U i $end
$scope module fa $end
$var wire 1 V A $end
$var wire 1 W B $end
$var wire 1 X Cin $end
$var wire 1 Y Cout $end
$var wire 1 Z Sum $end
$upscope $end
$upscope $end
$scope begin fa_stage[2] $end
$var parameter 3 [ i $end
$scope module fa $end
$var wire 1 \ A $end
$var wire 1 ] B $end
$var wire 1 ^ Cin $end
$var wire 1 _ Cout $end
$var wire 1 ` Sum $end
$upscope $end
$upscope $end
$scope begin fa_stage[3] $end
$var parameter 3 a i $end
$scope module fa $end
$var wire 1 b A $end
$var wire 1 c B $end
$var wire 1 d Cin $end
$var wire 1 e Cout $end
$var wire 1 f Sum $end
$upscope $end
$upscope $end
$scope begin fa_stage[4] $end
$var parameter 4 g i $end
$scope module fa $end
$var wire 1 h A $end
$var wire 1 i B $end
$var wire 1 j Cin $end
$var wire 1 k Cout $end
$var wire 1 l Sum $end
$upscope $end
$upscope $end
$scope begin fa_stage[5] $end
$var parameter 4 m i $end
$scope module fa $end
$var wire 1 n A $end
$var wire 1 o B $end
$var wire 1 p Cin $end
$var wire 1 q Cout $end
$var wire 1 r Sum $end
$upscope $end
$upscope $end
$scope begin fa_stage[6] $end
$var parameter 4 s i $end
$scope module fa $end
$var wire 1 t A $end
$var wire 1 u B $end
$var wire 1 v Cin $end
$var wire 1 w Cout $end
$var wire 1 x Sum $end
$upscope $end
$upscope $end
$scope begin fa_stage[7] $end
$var parameter 4 y i $end
$scope module fa $end
$var wire 1 z A $end
$var wire 1 { B $end
$var wire 1 | Cin $end
$var wire 1 } Cout $end
$var wire 1 ~ Sum $end
$upscope $end
$upscope $end
$upscope $end
$upscope $end
$enddefinitions $end
$comment Show the parameter values. $end
$dumpall
b111 y
b110 s
b101 m
b100 g
b11 a
b10 [
b1 U
b0 O
b1000 N
b11 D
b10 >
b1 8
b0 2
b100 1
b1000 &
b100 %
$end
#0
$dumpvars
x~
x}
x|
x{
xz
xx
xw
xv
xu
xt
xr
xq
xp
xo
xn
xl
xk
xj
xi
xh
xf
xe
xd
xc
xb
x`
x_
x^
x]
x\
xZ
xY
xX
xW
xV
xT
xS
xR
xQ
xP
bx M
bx L
bx K
bx J
0I
0H
0G
0F
0E
1C
0B
1A
0@
0?
0=
1<
0;
1:
19
17
06
05
14
03
b101 0
b100 /
b11 .
b10 -
x,
0+
bx *
b11 )
bx (
b10 '
0$
x#
b101 "
bx !
$end
#10000
0C
1=
0A
b1011 "
b1011 0
1I
1;
0<
1G
16
1B
15
0:
1@
13
09
1?
b1011 /
1+
b101 )
b101 .
b101 '
b101 -
#20000
1G
1B
1A
1$
0C
0=
1<
0I
1H
b0 "
b0 0
07
05
0@
19
1E
b11110 /
0+
b1 )
b1 .
b1111 '
b1111 -
#30000
1=
1C
1I
b1111 "
b1111 0
17
15
1:
1@
1F
b11111 /
1+
b1111 )
b1111 .
#40000
0=
0C
0I
0;
0A
0G
0$
06
0<
0B
0H
b0 "
b0 0
07
05
04
0:
0@
0F
03
09
0?
0E
b0 /
0+
b0 )
b0 .
b0 '
b0 -
#50000
0`
0r
0^
0p
1~
0Y
0k
1|
1w
1Z
1f
1l
0x
0X
1d
0j
1v
0#
0S
1_
0e
1q
0}
b10011011 !
b10011011 M
1T
0R
1Q
1W
1]
0c
1i
1o
0u
0{
0P
0V
1\
0b
0h
1n
1t
0z
b11001000 L
0,
b110111 *
b110111 K
b1100100 (
b1100100 J
#60000
1`
1r
1^
1p
1X
1Y
1j
1k
1x
1S
1Z
1e
b11111111 !
b11111111 M
1l
1R
1c
1u
1P
1V
1b
1h
b11111111 L
1,
b1111111 *
b1111111 K
b1111111 (
b1111111 J
#70000
1#
0Z
0`
0f
0l
0r
0x
0~
1}
b0 !
b0 M
0T
0R
0W
0]
0c
0i
0o
0u
1z
b111111110 L
0,
b1 *
b1 K
b11111111 (
b11111111 J
#80000
1Z
1`
1f
1l
1r
1x
1~
b11111111 !
b11111111 M
1T
1R
1W
1]
1c
1i
1o
1u
1{
b111111111 L
1,
b11111111 *
b11111111 K
