encoder/encoder.v
module encoder_8to3 (
    input  [7:0] d,
    output [2:0] y
);
    // y[0] is high if d[1], d[3], d[5], or d[7] is high
    assign y[0] = d[1] | d[3] | d[5] | d[7];

    // y[1] is high if d[2], d[3], d[6], or d[7] is high
    assign y[1] = d[2] | d[3] | d[6] | d[7];

    // y[2] is high if d[4], d[5], d[6], or d[7] is high
    assign y[2] = d[4] | d[5] | d[6] | d[7];

endmodule

encoder/encoder_tb.v
`timescale 1ns / 1ps

module encoder_tb;

    // Declarations
    reg  [7:0] d;
    wire [2:0] y;

    // Instantiate DUT
    encoder_8to3 uut (
        .d(d),
        .y(y)
    );

    integer i;

    initial begin
        $dumpfile("encoder_waves.vcd");
        $dumpvars(0, encoder_tb);

        // Test all 8 one-hot inputs
        for (i = 0; i < 8; i = i + 1) begin
            d = (1 << i);
            #10;
            $display("d=%b | y=%d", d, y);
        end

        // Test: no input active
        d = 8'b0000_0000; #10;
        $display("d=%b | y=%b (undefined)", d, y);

        $finish;
    end

endmodule

encoder/encoder_waves.vcd
$date
	Thu Apr  2 09:43:26 2026
$end
$version
	Icarus Verilog
$end
$timescale
	1ps
$end
$scope module encoder_tb $end
$var wire 3 ! y [2:0] $end
$var reg 8 " d [7:0] $end
$var integer 32 # i [31:0] $end
$scope module uut $end
$var wire 8 $ d [7:0] $end
$var reg 3 % y [2:0] $end
$upscope $end
$upscope $end
$enddefinitions $end
$comment Show the parameter values. $end
$dumpall
$end
#0
$dumpvars
b0 %
b1 $
b0 #
b1 "
b0 !
$end
#10000
b1 !
b1 %
b10 "
b10 $
b1 #
#20000
b10 !
b10 %
b100 "
b100 $
b10 #
#30000
b11 !
b11 %
b1000 "
b1000 $
b11 #
#40000
b100 !
b100 %
b10000 "
b10000 $
b100 #
#50000
b101 !
b101 %
b100000 "
b100000 $
b101 #
#60000
b110 !
b110 %
b1000000 "
b1000000 $
b110 #
#70000
b111 !
b111 %
b10000000 "
b10000000 $
b111 #
#80000
bx !
bx %
b0 "
b0 $
b1000 #
