encoder/encoder.v
// 8:3 Binary Encoder
// Assumes only one input is active at a time (one-hot)
module encoder_8to3 (
    input  [7:0] d,      // 8-bit one-hot input
    output reg [2:0] y   // 3-bit encoded output
);

    always @(*) begin
        case (d)
            8'b0000_0001: y = 3'd0;
            8'b0000_0010: y = 3'd1;
            8'b0000_0100: y = 3'd2;
            8'b0000_1000: y = 3'd3;
            8'b0001_0000: y = 3'd4;
            8'b0010_0000: y = 3'd5;
            8'b0100_0000: y = 3'd6;
            8'b1000_0000: y = 3'd7;
            default:      y = 3'bxxx;
        endcase
    end

endmodule

encoder/encoder_tb.v
`timescale 1ns / 1ps

module encoder_tb;

    // Declarations
    reg  [7:0] d;
    wire [2:0] y;

    // Instantiate DUT
    encoder_8to3 uut (
        .d(d),
        .y(y)
    );

    integer i;

    initial begin
        $dumpfile("encoder_waves.vcd");
        $dumpvars(0, encoder_tb);

        // Test all 8 one-hot inputs
        for (i = 0; i < 8; i = i + 1) begin
            d = (1 << i);
            #10;
            $display("d=%b | y=%d", d, y);
        end

        // Test: no input active
        d = 8'b0000_0000; #10;
        $display("d=%b | y=%b (undefined)", d, y);

        $finish;
    end

endmodule

encoder/encoder_waves.vcd
$date
	Thu Apr  2 09:30:22 2026
$end
$version
	Icarus Verilog
$end
$timescale
	1ps
$end
$scope module encoder_tb $end
$var wire 3 ! y [2:0] $end
$var reg 8 " d [7:0] $end
$var integer 32 # i [31:0] $end
$scope module uut $end
$var wire 8 $ d [7:0] $end
$var reg 3 % y [2:0] $end
$upscope $end
$upscope $end
$enddefinitions $end
$comment Show the parameter values. $end
$dumpall
$end
#0
$dumpvars
b0 %
b1 $
b0 #
b1 "
b0 !
$end
#10000
b1 !
b1 %
b10 "
b10 $
b1 #
#20000
b10 !
b10 %
b100 "
b100 $
b10 #
#30000
b11 !
b11 %
b1000 "
b1000 $
b11 #
#40000
b100 !
b100 %
b10000 "
b10000 $
b100 #
#50000
b101 !
b101 %
b100000 "
b100000 $
b101 #
#60000
b110 !
b110 %
b1000000 "
b1000000 $
b110 #
#70000
b111 !
b111 %
b10000000 "
b10000000 $
b111 #
#80000
bx !
bx %
b0 "
b0 $
b1000 #
