decoder/decoder.v
// 3:8 Decoder with Enable
module decoder_3to8 (
    input  [2:0] a,      // 3-bit input
    input  en,            // Enable signal
    output reg [7:0] y    // 8-bit decoded output (active-high)
);

    always @(*) begin
        if (en) begin
            case (a)
                3'd0: y = 8'b0000_0001;
                3'd1: y = 8'b0000_0010;
                3'd2: y = 8'b0000_0100;
                3'd3: y = 8'b0000_1000;
                3'd4: y = 8'b0001_0000;
                3'd5: y = 8'b0010_0000;
                3'd6: y = 8'b0100_0000;
                3'd7: y = 8'b1000_0000;
                default: y = 8'b0000_0000;
            endcase
        end else begin
            y = 8'b0000_0000;
        end
    end

endmodule

decoder/decoder_tb.v
`timescale 1ns / 1ps

module decoder_tb;

    // Declarations
    reg  [2:0] a;
    reg  en;
    wire [7:0] y;

    // Instantiate DUT
    decoder_3to8 uut (
        .a(a),
        .en(en),
        .y(y)
    );

    integer i;

    initial begin
        $dumpfile("decoder_waves.vcd");
        $dumpvars(0, decoder_tb);

        // Test: Enable LOW — output should be 0
        en = 0;
        for (i = 0; i < 8; i = i + 1) begin
            a = i[2:0];
            #10;
            $display("en=%b a=%d | y=%b", en, a, y);
        end

        // Test: Enable HIGH — normal decoding
        en = 1;
        for (i = 0; i < 8; i = i + 1) begin
            a = i[2:0];
            #10;
            $display("en=%b a=%d | y=%b", en, a, y);
        end

        $finish;
    end

endmodule

decoder/decoder_waves.vcd
$date
	Thu Apr  2 09:30:24 2026
$end
$version
	Icarus Verilog
$end
$timescale
	1ps
$end
$scope module decoder_tb $end
$var wire 8 ! y [7:0] $end
$var reg 3 " a [2:0] $end
$var reg 1 # en $end
$var integer 32 $ i [31:0] $end
$scope module uut $end
$var wire 3 % a [2:0] $end
$var wire 1 # en $end
$var reg 8 & y [7:0] $end
$upscope $end
$upscope $end
$enddefinitions $end
$comment Show the parameter values. $end
$dumpall
$end
#0
$dumpvars
b0 &
b0 %
b0 $
0#
b0 "
b0 !
$end
#10000
b1 "
b1 %
b1 $
#20000
b10 "
b10 %
b10 $
#30000
b11 "
b11 %
b11 $
#40000
b100 "
b100 %
b100 $
#50000
b101 "
b101 %
b101 $
#60000
b110 "
b110 %
b110 $
#70000
b111 "
b111 %
b111 $
#80000
b1 !
b1 &
b0 "
b0 %
1#
b0 $
#90000
b10 !
b10 &
b1 "
b1 %
b1 $
#100000
b100 !
b100 &
b10 "
b10 %
b10 $
#110000
b1000 !
b1000 &
b11 "
b11 %
b11 $
#120000
b10000 !
b10000 &
b100 "
b100 %
b100 $
#130000
b100000 !
b100000 &
b101 "
b101 %
b101 $
#140000
b1000000 !
b1000000 &
b110 "
b110 %
b110 $
#150000
b10000000 !
b10000000 &
b111 "
b111 %
b111 $
#160000
b1000 $
