jk_flip_flop/jk_flip_flop.v
module jk_flip_flop (
    input      clk,
    input      rst,
    input      j,
    input      k,
    output reg q,
    output     q_bar
);

    assign q_bar = ~q;

    always @(posedge clk) begin
        if (rst)
            q <= 1'b0;
        else
            q <= (j & ~q) | (~k & q);
    end

endmodule

jk_flip_flop/jk_flip_flop_tb.v
`timescale 1ns / 1ps

module jk_flip_flop_tb;

    // Declarations
    reg  clk;
    reg  rst;
    reg  j, k;
    wire q;
    wire q_bar;

    // Instantiate DUT
    jk_flip_flop uut (
        .clk(clk),
        .rst(rst),
        .j(j),
        .k(k),
        .q(q),
        .q_bar(q_bar)
    );

    // Clock generation: 10ns period
    always #5 clk = ~clk;

    initial begin
        $dumpfile("jk_flip_flop_waves.vcd");
        $dumpvars(0, jk_flip_flop_tb);

        // Initialize & reset
        clk = 0; rst = 1; j = 0; k = 0;
        #10;
        $display("t=%0t | rst=%b J=%b K=%b | q=%b q_bar=%b (reset)", $time, rst, j, k, q, q_bar);

        rst = 0;

        // J=0, K=0 → Hold
        j = 0; k = 0; #10;
        $display("t=%0t | J=%b K=%b | q=%b q_bar=%b (hold)", $time, j, k, q, q_bar);

        // J=1, K=0 → Set
        j = 1; k = 0; #10;
        $display("t=%0t | J=%b K=%b | q=%b q_bar=%b (set)", $time, j, k, q, q_bar);

        // J=0, K=0 → Hold
        j = 0; k = 0; #10;
        $display("t=%0t | J=%b K=%b | q=%b q_bar=%b (hold)", $time, j, k, q, q_bar);

        // J=0, K=1 → Reset
        j = 0; k = 1; #10;
        $display("t=%0t | J=%b K=%b | q=%b q_bar=%b (reset)", $time, j, k, q, q_bar);

        // J=1, K=0 → Set again
        j = 1; k = 0; #10;
        $display("t=%0t | J=%b K=%b | q=%b q_bar=%b (set)", $time, j, k, q, q_bar);

        // J=1, K=1 → Toggle
        j = 1; k = 1; #10;
        $display("t=%0t | J=%b K=%b | q=%b q_bar=%b (toggle)", $time, j, k, q, q_bar);

        // J=1, K=1 → Toggle again
        j = 1; k = 1; #10;
        $display("t=%0t | J=%b K=%b | q=%b q_bar=%b (toggle)", $time, j, k, q, q_bar);

        #20;
        $finish;
    end

endmodule

jk_flip_flop/jk_flip_flop_waves.vcd
$date
	Fri Apr 17 11:19:02 2026
$end
$version
	Icarus Verilog
$end
$timescale
	1ps
$end
$scope module jk_flip_flop_tb $end
$var wire 1 ! q_bar $end
$var wire 1 " q $end
$var reg 1 # clk $end
$var reg 1 $ j $end
$var reg 1 % k $end
$var reg 1 & rst $end
$scope module uut $end
$var wire 1 # clk $end
$var wire 1 $ j $end
$var wire 1 % k $end
$var wire 1 ! q_bar $end
$var wire 1 & rst $end
$var reg 1 " q $end
$upscope $end
$upscope $end
$enddefinitions $end
$comment Show the parameter values. $end
$dumpall
$end
#0
$dumpvars
1&
0%
0$
0#
x"
x!
$end
#5000
1!
0"
1#
#10000
0#
0&
#15000
1#
#20000
0#
1$
#25000
0!
1"
1#
#30000
0#
0$
#35000
1#
#40000
0#
1%
#45000
1!
0"
1#
#50000
0#
0%
1$
#55000
0!
1"
1#
#60000
0#
1%
#65000
1!
0"
1#
#70000
0#
#75000
0!
1"
1#
#80000
0#
#85000
1!
0"
1#
#90000
0#
#95000
0!
1"
1#
