alu/alu_4bit.v
module alu_4bit (
    input [3:0] a,      // Operand A
    input  [3:0] b,      // Operand B
    input  [3:0] select, 
    input cin,
    output reg [3:0] result,  // Result
    output reg carry          // Carry/borrow flag
);
    reg [4:0] temp;

    always @(*) begin
        result = 4'b0000;
        carry = 1'b0;
        temp = 5'b0;

        case (select[3:2])
            2'b00: begin
                // Arithmetic group from table, selected by S1:S0 and Cin.
                case (select[1:0])
                    2'b00: temp = {1'b0, a} + cin;                 // F=A or A+1
                    2'b01: temp = {1'b0, a} + {1'b0, b} + cin;     // F=A+B or A+B+1
                    2'b10: temp = {1'b0, a} + {1'b0, ~b} + cin;    // F=A+~B or A+~B+1
                    2'b11: temp = {1'b0, a} + 5'b0_1111 + cin;     // F=A-1 or A
                    default: temp = 5'b0;
                endcase
                {carry, result} = temp;
            end

            2'b01: begin
                case (select[1:0])
                    2'b00: result = a & b;
                    2'b01: result = a | b;
                    2'b10: result = a ^ b;
                    2'b11: result = ~a;
                    default: result = 4'b0;
                endcase
                carry = 1'b0;
            end

            2'b10: begin
                result = a >> 1;
                carry = 1'b0;
            end

            2'b11: begin
                result = a << 1;
                carry = 1'b0;
            end
        endcase
    end

endmodule

alu/alu_4bit_tb.v
`timescale 1ns / 1ps

module alu_4bit_tb;

    reg [3:0] a, b;
    reg [3:0] select;
    reg cin;
    wire [3:0] result;
    wire carry;
    reg [4:0] expected;

    integer total_tests;
    integer passed_tests;
    integer failed_tests;
    integer i;

    reg [3:0] vec_a [0:5];
    reg [3:0] vec_b [0:5];

    // Instantiate the ALU
    alu_4bit dut (
        .a(a),
        .b(b),
        .select(select),
        .cin(cin),
        .result(result),
        .carry(carry)
    );

    initial begin
        $dumpfile("alu_waves.vcd");
        $dumpvars(0, alu_4bit_tb);
        total_tests = 0;
        passed_tests = 0;
        failed_tests = 0;

        vec_a[0] = 4'h0; vec_b[0] = 4'h0;
        vec_a[1] = 4'h1; vec_b[1] = 4'h7;
        vec_a[2] = 4'h5; vec_b[2] = 4'h3;
        vec_a[3] = 4'h8; vec_b[3] = 4'h4;
        vec_a[4] = 4'hF; vec_b[4] = 4'h1;
        vec_a[5] = 4'hA; vec_b[5] = 4'h5;

        $display("\n=== Checking ALU against provided function table ===");

        // Arithmetic rows: 0000..0111 with cin as table input
        for (i = 0; i < 6; i = i + 1) begin
            run_and_check(vec_a[i], vec_b[i], 4'b0000, 1'b0, "0000: F=A");
            run_and_check(vec_a[i], vec_b[i], 4'b0000, 1'b1, "0000: F=A+1");
            run_and_check(vec_a[i], vec_b[i], 4'b0001, 1'b0, "0001: F=A+B");
            run_and_check(vec_a[i], vec_b[i], 4'b0001, 1'b1, "0001: F=A+B+1");
            run_and_check(vec_a[i], vec_b[i], 4'b0010, 1'b0, "0010: F=A+~B");
            run_and_check(vec_a[i], vec_b[i], 4'b0010, 1'b1, "0010: F=A+~B+1");
            run_and_check(vec_a[i], vec_b[i], 4'b0011, 1'b0, "0011: F=A-1");
            run_and_check(vec_a[i], vec_b[i], 4'b0011, 1'b1, "0011: F=A");
        end

        // Logical rows: 01xx, cin is don't-care in table, test both values.
        for (i = 0; i < 6; i = i + 1) begin
            run_and_check(vec_a[i], vec_b[i], 4'b0100, 1'b0, "0100x: F=A&B");
            run_and_check(vec_a[i], vec_b[i], 4'b0100, 1'b1, "0100x: F=A&B");
            run_and_check(vec_a[i], vec_b[i], 4'b0101, 1'b0, "0101x: F=A|B");
            run_and_check(vec_a[i], vec_b[i], 4'b0101, 1'b1, "0101x: F=A|B");
            run_and_check(vec_a[i], vec_b[i], 4'b0110, 1'b0, "0110x: F=A^B");
            run_and_check(vec_a[i], vec_b[i], 4'b0110, 1'b1, "0110x: F=A^B");
            run_and_check(vec_a[i], vec_b[i], 4'b0111, 1'b0, "0111x: F=~A");
            run_and_check(vec_a[i], vec_b[i], 4'b0111, 1'b1, "0111x: F=~A");
        end

        // Shift rows: 10xx and 11xx, both lower bits and cin are don't-care.
        for (i = 0; i < 6; i = i + 1) begin
            run_and_check(vec_a[i], vec_b[i], 4'b1000, 1'b0, "10xxx: F=shr A");
            run_and_check(vec_a[i], vec_b[i], 4'b1001, 1'b1, "10xxx: F=shr A");
            run_and_check(vec_a[i], vec_b[i], 4'b1010, 1'b0, "10xxx: F=shr A");
            run_and_check(vec_a[i], vec_b[i], 4'b1011, 1'b1, "10xxx: F=shr A");

            run_and_check(vec_a[i], vec_b[i], 4'b1100, 1'b0, "11xxx: F=shl A");
            run_and_check(vec_a[i], vec_b[i], 4'b1101, 1'b1, "11xxx: F=shl A");
            run_and_check(vec_a[i], vec_b[i], 4'b1110, 1'b0, "11xxx: F=shl A");
            run_and_check(vec_a[i], vec_b[i], 4'b1111, 1'b1, "11xxx: F=shl A");
        end

        $display("\nTotal: %0d, Passed: %0d, Failed: %0d", total_tests, passed_tests, failed_tests);
        if (failed_tests == 0)
            $display("ALU matches the provided table.");
        else
            $display("ALU does NOT exactly match the provided table.");

        $finish;
    end

    task run_and_check(
        input [3:0] in_a,
        input [3:0] in_b,
        input [3:0] sel,
        input in_cin,
        input [8*24-1:0] label
    );
        begin
            a = in_a;
            b = in_b;
            select = sel;
            cin = in_cin;
            #1;

            expected = expected_from_table(in_a, in_b, sel, in_cin);
            total_tests = total_tests + 1;

            if ({carry, result} === expected) begin
                passed_tests = passed_tests + 1;
            end else begin
                failed_tests = failed_tests + 1;
                $display("FAIL %0d | %s | A=%b B=%b S=%b Cin=%b | exp={%b,%b} got={%b,%b}",
                         total_tests, label, in_a, in_b, sel, in_cin,
                         expected[4], expected[3:0], carry, result);
            end
        end
    endtask

    function [4:0] expected_from_table(
        input [3:0] in_a,
        input [3:0] in_b,
        input [3:0] sel,
        input in_cin
    );
        reg [4:0] temp;
        begin
            temp = 5'b0;
            case (sel[3:2])
                2'b00: begin
                    case (sel[1:0])
                        2'b00: temp = {1'b0, in_a} + in_cin;
                        2'b01: temp = {1'b0, in_a} + {1'b0, in_b} + in_cin;
                        2'b10: temp = {1'b0, in_a} + {1'b0, ~in_b} + in_cin;
                        2'b11: temp = {1'b0, in_a} + 5'b0_1111 + in_cin;
                    endcase
                end
                2'b01: begin
                    case (sel[1:0])
                        2'b00: temp = {1'b0, (in_a & in_b)};
                        2'b01: temp = {1'b0, (in_a | in_b)};
                        2'b10: temp = {1'b0, (in_a ^ in_b)};
                        2'b11: temp = {1'b0, (~in_a)};
                    endcase
                end
                2'b10: temp = {1'b0, (in_a >> 1)};
                2'b11: temp = {1'b0, (in_a << 1)};
            endcase

            expected_from_table = temp;
        end
    endfunction

endmodule

alu/alu_waves.vcd
$date
	Fri Apr 24 01:26:52 2026
$end
$version
	Icarus Verilog
$end
$timescale
	1ps
$end
$scope module alu_4bit_tb $end
$var wire 4 ! result [3:0] $end
$var wire 1 " carry $end
$var reg 4 # a [3:0] $end
$var reg 4 $ b [3:0] $end
$var reg 1 % cin $end
$var reg 5 & expected [4:0] $end
$var reg 4 ' select [3:0] $end
$var integer 32 ( failed_tests [31:0] $end
$var integer 32 ) i [31:0] $end
$var integer 32 * passed_tests [31:0] $end
$var integer 32 + total_tests [31:0] $end
$scope function expected_from_table $end
$var reg 4 , in_a [3:0] $end
$var reg 4 - in_b [3:0] $end
$var reg 1 . in_cin $end
$var reg 4 / sel [3:0] $end
$var reg 5 0 temp [4:0] $end
$upscope $end
$scope module dut $end
$var wire 4 1 a [3:0] $end
$var wire 4 2 b [3:0] $end
$var wire 1 % cin $end
$var wire 4 3 select [3:0] $end
$var reg 1 " carry $end
$var reg 4 4 result [3:0] $end
$var reg 5 5 temp [4:0] $end
$upscope $end
$scope task run_and_check $end
$var reg 4 6 in_a [3:0] $end
$var reg 4 7 in_b [3:0] $end
$var reg 1 8 in_cin $end
$var reg 192 9 label [191:0] $end
$var reg 4 : sel [3:0] $end
$upscope $end
$upscope $end
$enddefinitions $end
$comment Show the parameter values. $end
$dumpall
$end
#0
$dumpvars
b0 :
b1100000011000000110000001100000011101000100000010001100011110101000001 9
08
b0 7
b0 6
b0 5
b0 4
b0 3
b0 2
b0 1
bx 0
bx /
x.
bx -
bx ,
b0 +
b0 *
b0 )
b0 (
b0 '
bx &
0%
b0 $
b0 #
0"
b0 !
$end
#1000
b1 !
b1 4
b1 5
1%
b11000000110000001100000011000000111010001000000100011000111101010000010010101100110001 9
18
b1 *
b1 +
b0 &
b0 0
b0 ,
b0 -
b0 /
0.
#2000
b0 5
b0 !
b0 4
0%
b1 '
b1 3
b11000000110000001100000011000100111010001000000100011000111101010000010010101101000010 9
08
b1 :
b10 *
b10 +
b1 &
b1 0
1.
#3000
b1 !
b1 4
b1 5
1%
b110000001100000011000000110001001110100010000001000110001111010100000100101011010000100010101100110001 9
18
b11 *
b11 +
b0 &
b0 0
b1 /
0.
#4000
b1111 5
b1111 !
b1111 4
0%
b10 '
b10 3
b1100000011000000110001001100000011101000100000010001100011110101000001001010110111111001000010 9
08
b10 :
b100 *
b100 +
b1 &
b1 0
1.
#5000
1"
b10000 5
b0 !
b0 4
1%
b11000000110000001100010011000000111010001000000100011000111101010000010010101101111110010000100010101100110001 9
18
b101 *
b101 +
b1111 &
b1111 0
b10 /
0.
#6000
b1111 !
b1111 4
b1111 5
0"
0%
b11 '
b11 3
b11000000110000001100010011000100111010001000000100011000111101010000010010110100110001 9
08
b11 :
b110 *
b110 +
b10000 &
b10000 0
1.
#7000
1"
b10000 5
b0 !
b0 4
1%
b1100000011000000110001001100010011101000100000010001100011110101000001 9
18
b111 *
b111 +
b1111 &
b1111 0
b11 /
0.
#8000
b1 !
b1 4
b1 5
0"
0%
b0 '
b0 3
b111 $
b111 2
b1 #
b1 1
b1100000011000000110000001100000011101000100000010001100011110101000001 9
08
b0 :
b111 7
b1 6
b1 )
b1000 *
b1000 +
b10000 &
b10000 0
1.
#9000
b10 5
b10 !
b10 4
1%
b11000000110000001100000011000000111010001000000100011000111101010000010010101100110001 9
18
b1001 *
b1001 +
b1 &
b1 0
b1 ,
b111 -
b0 /
0.
#10000
b1000 5
b1000 !
b1000 4
0%
b1 '
b1 3
b11000000110000001100000011000100111010001000000100011000111101010000010010101101000010 9
08
b1 :
b1010 *
b1010 +
b10 &
b10 0
1.
#11000
b1001 5
b1001 !
b1001 4
1%
b110000001100000011000000110001001110100010000001000110001111010100000100101011010000100010101100110001 9
18
b1011 *
b1011 +
b1000 &
b1000 0
b1 /
0.
#12000
b1001 5
b1001 !
b1001 4
0%
b10 '
b10 3
b1100000011000000110001001100000011101000100000010001100011110101000001001010110111111001000010 9
08
b10 :
b1100 *
b1100 +
b1001 &
b1001 0
1.
#13000
b1010 5
b1010 !
b1010 4
1%
b11000000110000001100010011000000111010001000000100011000111101010000010010101101111110010000100010101100110001 9
18
b1101 *
b1101 +
b1001 0
b10 /
0.
#14000
1"
b10000 5
b0 !
b0 4
0%
b11 '
b11 3
b11000000110000001100010011000100111010001000000100011000111101010000010010110100110001 9
08
b11 :
b1110 *
b1110 +
b1010 &
b1010 0
1.
#15000
b1 !
b1 4
b10001 5
1"
1%
b1100000011000000110001001100010011101000100000010001100011110101000001 9
18
b1111 *
b1111 +
b10000 &
b10000 0
b11 /
0.
#16000
b101 5
0"
b101 !
b101 4
0%
b0 '
b0 3
b11 $
b11 2
b101 #
b101 1
b1100000011000000110000001100000011101000100000010001100011110101000001 9
08
b0 :
b11 7
b101 6
b10 )
b10000 *
b10000 +
b10001 &
b10001 0
1.
#17000
b110 5
b110 !
b110 4
1%
b11000000110000001100000011000000111010001000000100011000111101010000010010101100110001 9
18
b10001 *
b10001 +
b101 &
b101 0
b101 ,
b11 -
b0 /
0.
#18000
b1000 5
b1000 !
b1000 4
0%
b1 '
b1 3
b11000000110000001100000011000100111010001000000100011000111101010000010010101101000010 9
08
b1 :
b10010 *
b10010 +
b110 &
b110 0
1.
#19000
b1001 5
b1001 !
b1001 4
1%
b110000001100000011000000110001001110100010000001000110001111010100000100101011010000100010101100110001 9
18
b10011 *
b10011 +
b1000 &
b1000 0
b1 /
0.
#20000
1"
b10001 5
b1 !
b1 4
0%
b10 '
b10 3
b1100000011000000110001001100000011101000100000010001100011110101000001001010110111111001000010 9
08
b10 :
b10100 *
b10100 +
b1001 &
b1001 0
1.
#21000
b10010 5
1"
b10 !
b10 4
1%
b11000000110000001100010011000000111010001000000100011000111101010000010010101101111110010000100010101100110001 9
18
b10101 *
b10101 +
b10001 &
b10001 0
b10 /
0.
#22000
b10100 5
1"
b100 !
b100 4
0%
b11 '
b11 3
b11000000110000001100010011000100111010001000000100011000111101010000010010110100110001 9
08
b11 :
b10110 *
b10110 +
b10010 &
b10010 0
1.
#23000
b10101 5
1"
b101 !
b101 4
1%
b1100000011000000110001001100010011101000100000010001100011110101000001 9
18
b10111 *
b10111 +
b10100 &
b10100 0
b11 /
0.
#24000
b1000 5
0"
b1000 !
b1000 4
0%
b0 '
b0 3
b100 $
b100 2
b1000 #
b1000 1
b1100000011000000110000001100000011101000100000010001100011110101000001 9
08
b0 :
b100 7
b1000 6
b11 )
b11000 *
b11000 +
b10101 &
b10101 0
1.
#25000
b1001 5
b1001 !
b1001 4
1%
b11000000110000001100000011000000111010001000000100011000111101010000010010101100110001 9
18
b11001 *
b11001 +
b1000 &
b1000 0
b1000 ,
b100 -
b0 /
0.
#26000
b1100 5
b1100 !
b1100 4
0%
b1 '
b1 3
b11000000110000001100000011000100111010001000000100011000111101010000010010101101000010 9
08
b1 :
b11010 *
b11010 +
b1001 &
b1001 0
1.
#27000
b1101 5
b1101 !
b1101 4
1%
b110000001100000011000000110001001110100010000001000110001111010100000100101011010000100010101100110001 9
18
b11011 *
b11011 +
b1100 &
b1100 0
b1 /
0.
#28000
1"
b10011 5
b11 !
b11 4
0%
b10 '
b10 3
b1100000011000000110001001100000011101000100000010001100011110101000001001010110111111001000010 9
08
b10 :
b11100 *
b11100 +
b1101 &
b1101 0
1.
#29000
b10100 5
1"
b100 !
b100 4
1%
b11000000110000001100010011000000111010001000000100011000111101010000010010101101111110010000100010101100110001 9
18
b11101 *
b11101 +
b10011 &
b10011 0
b10 /
0.
#30000
b10111 5
1"
b111 !
b111 4
0%
b11 '
b11 3
b11000000110000001100010011000100111010001000000100011000111101010000010010110100110001 9
08
b11 :
b11110 *
b11110 +
b10100 &
b10100 0
1.
#31000
b11000 5
1"
b1000 !
b1000 4
1%
b1100000011000000110001001100010011101000100000010001100011110101000001 9
18
b11111 *
b11111 +
b10111 &
b10111 0
b11 /
0.
#32000
b1111 5
0"
b1111 !
b1111 4
0%
b0 '
b0 3
b1 $
b1 2
b1111 #
b1111 1
b1100000011000000110000001100000011101000100000010001100011110101000001 9
08
b0 :
b1 7
b1111 6
b100 )
b100000 *
b100000 +
b11000 &
b11000 0
1.
#33000
1"
b10000 5
b0 !
b0 4
1%
b11000000110000001100000011000000111010001000000100011000111101010000010010101100110001 9
18
b100001 *
b100001 +
b1111 &
b1111 0
b1111 ,
b1 -
b0 /
0.
#34000
b10000 5
1"
0%
b1 '
b1 3
b11000000110000001100000011000100111010001000000100011000111101010000010010101101000010 9
08
b1 :
b100010 *
b100010 +
b10000 &
b10000 0
1.
#35000
b1 !
b1 4
b10001 5
1"
1%
b110000001100000011000000110001001110100010000001000110001111010100000100101011010000100010101100110001 9
18
b100011 *
b100011 +
b10000 0
b1 /
0.
#36000
b11101 5
1"
b1101 !
b1101 4
0%
b10 '
b10 3
b1100000011000000110001001100000011101000100000010001100011110101000001001010110111111001000010 9
08
b10 :
b100100 *
b100100 +
b10001 &
b10001 0
1.
#37000
b11110 5
1"
b1110 !
b1110 4
1%
b11000000110000001100010011000000111010001000000100011000111101010000010010101101111110010000100010101100110001 9
18
b100101 *
b100101 +
b11101 &
b11101 0
b10 /
0.
#38000
b11110 5
1"
b1110 !
b1110 4
0%
b11 '
b11 3
b11000000110000001100010011000100111010001000000100011000111101010000010010110100110001 9
08
b11 :
b100110 *
b100110 +
b11110 &
b11110 0
1.
#39000
b11111 5
1"
b1111 !
b1111 4
1%
b1100000011000000110001001100010011101000100000010001100011110101000001 9
18
b100111 *
b100111 +
b11110 0
b11 /
0.
#40000
b1010 5
0"
b1010 !
b1010 4
0%
b0 '
b0 3
b101 $
b101 2
b1010 #
b1010 1
b1100000011000000110000001100000011101000100000010001100011110101000001 9
08
b0 :
b101 7
b1010 6
b101 )
b101000 *
b101000 +
b11111 &
b11111 0
1.
#41000
b1011 5
b1011 !
b1011 4
1%
b11000000110000001100000011000000111010001000000100011000111101010000010010101100110001 9
18
b101001 *
b101001 +
b1010 &
b1010 0
b1010 ,
b101 -
b0 /
0.
#42000
b1111 5
b1111 !
b1111 4
0%
b1 '
b1 3
b11000000110000001100000011000100111010001000000100011000111101010000010010101101000010 9
08
b1 :
b101010 *
b101010 +
b1011 &
b1011 0
1.
#43000
1"
b10000 5
b0 !
b0 4
1%
b110000001100000011000000110001001110100010000001000110001111010100000100101011010000100010101100110001 9
18
b101011 *
b101011 +
b1111 &
b1111 0
b1 /
0.
#44000
b100 !
b100 4
b10100 5
1"
0%
b10 '
b10 3
b1100000011000000110001001100000011101000100000010001100011110101000001001010110111111001000010 9
08
b10 :
b101100 *
b101100 +
b10000 &
b10000 0
1.
#45000
b10101 5
1"
b101 !
b101 4
1%
b11000000110000001100010011000000111010001000000100011000111101010000010010101101111110010000100010101100110001 9
18
b101101 *
b101101 +
b10100 &
b10100 0
b10 /
0.
#46000
b11001 5
1"
b1001 !
b1001 4
0%
b11 '
b11 3
b11000000110000001100010011000100111010001000000100011000111101010000010010110100110001 9
08
b11 :
b101110 *
b101110 +
b10101 &
b10101 0
1.
#47000
b11010 5
1"
b1010 !
b1010 4
1%
b1100000011000000110001001100010011101000100000010001100011110101000001 9
18
b101111 *
b101111 +
b11001 &
b11001 0
b11 /
0.
#48000
b0 5
0"
b0 !
b0 4
0%
b100 '
b100 3
b0 $
b0 2
b0 #
b0 1
b1100000011000100110000001100000111100000111010001000000100011000111101010000010010011001000010 9
08
b100 :
b0 7
b0 6
b0 )
b110000 *
b110000 +
b11010 &
b11010 0
1.
#49000
1%
18
b110001 *
b110001 +
b0 &
b0 0
b0 ,
b0 -
b100 /
0.
#50000
0%
b101 '
b101 3
b1100000011000100110000001100010111100000111010001000000100011000111101010000010111110001000010 9
08
b101 :
b110010 *
b110010 +
1.
#51000
1%
18
b110011 *
b110011 +
b101 /
0.
#52000
0%
b110 '
b110 3
b1100000011000100110001001100000111100000111010001000000100011000111101010000010101111001000010 9
08
b110 :
b110100 *
b110100 +
1.
#53000
1%
18
b110101 *
b110101 +
b110 /
0.
#54000
b1111 !
b1111 4
0%
b111 '
b111 3
b11000000110001001100010011000101111000001110100010000001000110001111010111111001000001 9
08
b111 :
b110110 *
b110110 +
1.
#55000
b1111 !
b1111 4
1%
18
b110111 *
b110111 +
b1111 &
b1111 0
b111 /
0.
#56000
b1 !
b1 4
0%
b100 '
b100 3
b111 $
b111 2
b1 #
b1 1
b1100000011000100110000001100000111100000111010001000000100011000111101010000010010011001000010 9
08
b100 :
b111 7
b1 6
b1 )
b111000 *
b111000 +
b1111 0
1.
#57000
b1 !
b1 4
1%
18
b111001 *
b111001 +
b1 &
b1 0
b1 ,
b111 -
b100 /
0.
#58000
b111 !
b111 4
0%
b101 '
b101 3
b1100000011000100110000001100010111100000111010001000000100011000111101010000010111110001000010 9
08
b101 :
b111010 *
b111010 +
b1 0
1.
#59000
b111 !
b111 4
1%
18
b111011 *
b111011 +
b111 &
b111 0
b101 /
0.
#60000
b110 !
b110 4
0%
b110 '
b110 3
b1100000011000100110001001100000111100000111010001000000100011000111101010000010101111001000010 9
08
b110 :
b111100 *
b111100 +
b111 0
1.
#61000
b110 !
b110 4
1%
18
b111101 *
b111101 +
b110 &
b110 0
b110 /
0.
#62000
b1110 !
b1110 4
0%
b111 '
b111 3
b11000000110001001100010011000101111000001110100010000001000110001111010111111001000001 9
08
b111 :
b111110 *
b111110 +
b110 0
1.
#63000
b1110 !
b1110 4
1%
18
b111111 *
b111111 +
b1110 &
b1110 0
b111 /
0.
#64000
b1 !
b1 4
0%
b100 '
b100 3
b11 $
b11 2
b101 #
b101 1
b1100000011000100110000001100000111100000111010001000000100011000111101010000010010011001000010 9
08
b100 :
b11 7
b101 6
b10 )
b1000000 *
b1000000 +
b1110 0
1.
#65000
b1 !
b1 4
1%
18
b1000001 *
b1000001 +
b1 &
b1 0
b101 ,
b11 -
b100 /
0.
#66000
b111 !
b111 4
0%
b101 '
b101 3
b1100000011000100110000001100010111100000111010001000000100011000111101010000010111110001000010 9
08
b101 :
b1000010 *
b1000010 +
b1 0
1.
#67000
b111 !
b111 4
1%
18
b1000011 *
b1000011 +
b111 &
b111 0
b101 /
0.
#68000
b110 !
b110 4
0%
b110 '
b110 3
b1100000011000100110001001100000111100000111010001000000100011000111101010000010101111001000010 9
08
b110 :
b1000100 *
b1000100 +
b111 0
1.
#69000
b110 !
b110 4
1%
18
b1000101 *
b1000101 +
b110 &
b110 0
b110 /
0.
#70000
b1010 !
b1010 4
0%
b111 '
b111 3
b11000000110001001100010011000101111000001110100010000001000110001111010111111001000001 9
08
b111 :
b1000110 *
b1000110 +
b110 0
1.
#71000
b1010 !
b1010 4
1%
18
b1000111 *
b1000111 +
b1010 &
b1010 0
b111 /
0.
#72000
b0 !
b0 4
0%
b100 '
b100 3
b100 $
b100 2
b1000 #
b1000 1
b1100000011000100110000001100000111100000111010001000000100011000111101010000010010011001000010 9
08
b100 :
b100 7
b1000 6
b11 )
b1001000 *
b1001000 +
b1010 0
1.
#73000
1%
18
b1001001 *
b1001001 +
b0 &
b0 0
b1000 ,
b100 -
b100 /
0.
#74000
b1100 !
b1100 4
0%
b101 '
b101 3
b1100000011000100110000001100010111100000111010001000000100011000111101010000010111110001000010 9
08
b101 :
b1001010 *
b1001010 +
1.
#75000
b1100 !
b1100 4
1%
18
b1001011 *
b1001011 +
b1100 &
b1100 0
b101 /
0.
#76000
b1100 !
b1100 4
0%
b110 '
b110 3
b1100000011000100110001001100000111100000111010001000000100011000111101010000010101111001000010 9
08
b110 :
b1001100 *
b1001100 +
b1100 0
1.
#77000
b1100 !
b1100 4
1%
18
b1001101 *
b1001101 +
b1100 0
b110 /
0.
#78000
b111 !
b111 4
0%
b111 '
b111 3
b11000000110001001100010011000101111000001110100010000001000110001111010111111001000001 9
08
b111 :
b1001110 *
b1001110 +
b1100 0
1.
#79000
b111 !
b111 4
1%
18
b1001111 *
b1001111 +
b111 &
b111 0
b111 /
0.
#80000
b1 !
b1 4
0%
b100 '
b100 3
b1 $
b1 2
b1111 #
b1111 1
b1100000011000100110000001100000111100000111010001000000100011000111101010000010010011001000010 9
08
b100 :
b1 7
b1111 6
b100 )
b1010000 *
b1010000 +
b111 0
1.
#81000
b1 !
b1 4
1%
18
b1010001 *
b1010001 +
b1 &
b1 0
b1111 ,
b1 -
b100 /
0.
#82000
b1111 !
b1111 4
0%
b101 '
b101 3
b1100000011000100110000001100010111100000111010001000000100011000111101010000010111110001000010 9
08
b101 :
b1010010 *
b1010010 +
b1 0
1.
#83000
b1111 !
b1111 4
1%
18
b1010011 *
b1010011 +
b1111 &
b1111 0
b101 /
0.
#84000
b1110 !
b1110 4
0%
b110 '
b110 3
b1100000011000100110001001100000111100000111010001000000100011000111101010000010101111001000010 9
08
b110 :
b1010100 *
b1010100 +
b1111 0
1.
#85000
b1110 !
b1110 4
1%
18
b1010101 *
b1010101 +
b1110 &
b1110 0
b110 /
0.
#86000
b0 !
b0 4
0%
b111 '
b111 3
b11000000110001001100010011000101111000001110100010000001000110001111010111111001000001 9
08
b111 :
b1010110 *
b1010110 +
b1110 0
1.
#87000
1%
18
b1010111 *
b1010111 +
b0 &
b0 0
b111 /
0.
#88000
0%
b100 '
b100 3
b101 $
b101 2
b1010 #
b1010 1
b1100000011000100110000001100000111100000111010001000000100011000111101010000010010011001000010 9
08
b100 :
b101 7
b1010 6
b101 )
b1011000 *
b1011000 +
1.
#89000
1%
18
b1011001 *
b1011001 +
b1010 ,
b101 -
b100 /
0.
#90000
b1111 !
b1111 4
0%
b101 '
b101 3
b1100000011000100110000001100010111100000111010001000000100011000111101010000010111110001000010 9
08
b101 :
b1011010 *
b1011010 +
1.
#91000
b1111 !
b1111 4
1%
18
b1011011 *
b1011011 +
b1111 &
b1111 0
b101 /
0.
#92000
b1111 !
b1111 4
0%
b110 '
b110 3
b1100000011000100110001001100000111100000111010001000000100011000111101010000010101111001000010 9
08
b110 :
b1011100 *
b1011100 +
b1111 0
1.
#93000
b1111 !
b1111 4
1%
18
b1011101 *
b1011101 +
b1111 0
b110 /
0.
#94000
b101 !
b101 4
0%
b111 '
b111 3
b11000000110001001100010011000101111000001110100010000001000110001111010111111001000001 9
08
b111 :
b1011110 *
b1011110 +
b1111 0
1.
#95000
b101 !
b101 4
1%
18
b1011111 *
b1011111 +
b101 &
b101 0
b111 /
0.
#96000
b0 !
b0 4
0%
b1000 '
b1000 3
b0 $
b0 2
b0 #
b0 1
b11000100110000011110000111100001111000001110100010000001000110001111010111001101101000011100100010000001000001 9
08
b1000 :
b0 7
b0 6
b0 )
b1100000 *
b1100000 +
b101 0
1.
#97000
1%
b1001 '
b1001 3
18
b1001 :
b1100001 *
b1100001 +
b0 &
b0 0
b0 ,
b0 -
b1000 /
0.
#98000
0%
b1010 '
b1010 3
08
b1010 :
b1100010 *
b1100010 +
b1001 /
1.
#99000
1%
b1011 '
b1011 3
18
b1011 :
b1100011 *
b1100011 +
b1010 /
0.
#100000
0%
b1100 '
b1100 3
b11000100110001011110000111100001111000001110100010000001000110001111010111001101101000011011000010000001000001 9
08
b1100 :
b1100100 *
b1100100 +
b1011 /
1.
#101000
1%
b1101 '
b1101 3
18
b1101 :
b1100101 *
b1100101 +
b1100 /
0.
#102000
0%
b1110 '
b1110 3
08
b1110 :
b1100110 *
b1100110 +
b1101 /
1.
#103000
1%
b1111 '
b1111 3
18
b1111 :
b1100111 *
b1100111 +
b1110 /
0.
#104000
0%
b1000 '
b1000 3
b111 $
b111 2
b1 #
b1 1
b11000100110000011110000111100001111000001110100010000001000110001111010111001101101000011100100010000001000001 9
08
b1000 :
b111 7
b1 6
b1 )
b1101000 *
b1101000 +
b1111 /
1.
#105000
1%
b1001 '
b1001 3
18
b1001 :
b1101001 *
b1101001 +
b1 ,
b111 -
b1000 /
0.
#106000
0%
b1010 '
b1010 3
08
b1010 :
b1101010 *
b1101010 +
b1001 /
1.
#107000
1%
b1011 '
b1011 3
18
b1011 :
b1101011 *
b1101011 +
b1010 /
0.
#108000
b10 !
b10 4
0%
b1100 '
b1100 3
b11000100110001011110000111100001111000001110100010000001000110001111010111001101101000011011000010000001000001 9
08
b1100 :
b1101100 *
b1101100 +
b1011 /
1.
#109000
b10 !
b10 4
1%
b1101 '
b1101 3
18
b1101 :
b1101101 *
b1101101 +
b10 &
b10 0
b1100 /
0.
#110000
b10 !
b10 4
0%
b1110 '
b1110 3
08
b1110 :
b1101110 *
b1101110 +
b10 0
b1101 /
1.
#111000
b10 !
b10 4
1%
b1111 '
b1111 3
18
b1111 :
b1101111 *
b1101111 +
b10 0
b1110 /
0.
#112000
b10 !
b10 4
0%
b1000 '
b1000 3
b11 $
b11 2
b101 #
b101 1
b11000100110000011110000111100001111000001110100010000001000110001111010111001101101000011100100010000001000001 9
08
b1000 :
b11 7
b101 6
b10 )
b1110000 *
b1110000 +
b10 0
b1111 /
1.
#113000
b10 !
b10 4
1%
b1001 '
b1001 3
18
b1001 :
b1110001 *
b1110001 +
b10 0
b101 ,
b11 -
b1000 /
0.
#114000
b10 !
b10 4
0%
b1010 '
b1010 3
08
b1010 :
b1110010 *
b1110010 +
b10 0
b1001 /
1.
#115000
b10 !
b10 4
1%
b1011 '
b1011 3
18
b1011 :
b1110011 *
b1110011 +
b10 0
b1010 /
0.
#116000
b1010 !
b1010 4
0%
b1100 '
b1100 3
b11000100110001011110000111100001111000001110100010000001000110001111010111001101101000011011000010000001000001 9
08
b1100 :
b1110100 *
b1110100 +
b10 0
b1011 /
1.
#117000
b1010 !
b1010 4
1%
b1101 '
b1101 3
18
b1101 :
b1110101 *
b1110101 +
b1010 &
b1010 0
b1100 /
0.
#118000
b1010 !
b1010 4
0%
b1110 '
b1110 3
08
b1110 :
b1110110 *
b1110110 +
b1010 0
b1101 /
1.
#119000
b1010 !
b1010 4
1%
b1111 '
b1111 3
18
b1111 :
b1110111 *
b1110111 +
b1010 0
b1110 /
0.
#120000
b100 !
b100 4
0%
b1000 '
b1000 3
b100 $
b100 2
b1000 #
b1000 1
b11000100110000011110000111100001111000001110100010000001000110001111010111001101101000011100100010000001000001 9
08
b1000 :
b100 7
b1000 6
b11 )
b1111000 *
b1111000 +
b1010 0
b1111 /
1.
#121000
b100 !
b100 4
1%
b1001 '
b1001 3
18
b1001 :
b1111001 *
b1111001 +
b100 &
b100 0
b1000 ,
b100 -
b1000 /
0.
#122000
b100 !
b100 4
0%
b1010 '
b1010 3
08
b1010 :
b1111010 *
b1111010 +
b100 0
b1001 /
1.
#123000
b100 !
b100 4
1%
b1011 '
b1011 3
18
b1011 :
b1111011 *
b1111011 +
b100 0
b1010 /
0.
#124000
b0 !
b0 4
0%
b1100 '
b1100 3
b11000100110001011110000111100001111000001110100010000001000110001111010111001101101000011011000010000001000001 9
08
b1100 :
b1111100 *
b1111100 +
b100 0
b1011 /
1.
#125000
1%
b1101 '
b1101 3
18
b1101 :
b1111101 *
b1111101 +
b0 &
b0 0
b1100 /
0.
#126000
0%
b1110 '
b1110 3
08
b1110 :
b1111110 *
b1111110 +
b1101 /
1.
#127000
1%
b1111 '
b1111 3
18
b1111 :
b1111111 *
b1111111 +
b1110 /
0.
