alu/alu_4bit.v
module alu_4bit (
    input [3:0] a,      // Operand A
    input  [3:0] b,      // Operand B
    input  [3:0] select, 
    input cin,
    output reg [3:0] result,  // Result
    output reg carry          // Carry/borrow flag
);
    always @(*) begin
        result = 4'b0000;
        carry = 1'b0;

        case (select)
            4'b0000: begin // Transfer A
                result = a;
            end

            4'b0001: begin // A + 1
                {carry, result} = a + 4'b0001;
            end

            4'b0010: begin // A + B
                {carry, result} = a + b;
            end

            4'b0011: begin // A + B + 1
                {carry, result} = a + b + 4'b0001;
            end

            4'b0100: begin // A - B
                result = a - b;
                carry = 1'b0;
            end

            4'b0101: begin // A - B (alternate encoding)
                result = a - b;
                carry = 1'b0;
            end

            4'b0110: begin // A - 1
                result = a - 4'b0001;
                carry = (a == 4'b0000);
            end

            4'b0111: begin // Transfer A (alternate encoding)
                result = a;
            end

            4'b1000: begin // Arithmetic shift right
                result = {a[3], a[3:1]};
            end

            4'b1001: begin // AND
                result = a & b;
            end

            4'b1010: begin // OR
                result = a | b;
            end

            4'b1011: begin // XOR
                result = a ^ b;
            end

            4'b1100: begin // Rotate left
                result = {a[2:0], a[3]};
            end

            4'b1101: begin // NOT A
                result = ~a;
            end

            default: begin
                result = 4'b0000;
                carry = 1'b0;
            end
        endcase
    end

endmodule

alu/alu_4bit_comprehensive_tb.v
`timescale 1ns / 1ps

module alu_4bit_comprehensive_tb;

    // Test signals
    reg [3:0] a, b;
    reg [3:0] select;
    reg cin;
    wire [3:0] result;
    wire carry;
    
    // Test counters
    integer total_tests = 0;
    integer passed_tests = 0;
    integer failed_tests = 0;

    // Instantiate the ALU
    alu_4bit uut (
        .a(a),
        .b(b),
        .select(select),
        .cin(cin),
        .result(result),
        .carry(carry)
    );

    initial begin
        $dumpfile("alu_waves.vcd");
        $dumpvars(0, alu_4bit_comprehensive_tb);

        $display("\n\n");
        $display("╔════════════════════════════════════════════════════════╗");
        $display("║      ALU 4-bit Comprehensive Testbench                ║");
        $display("║    Testing All Operations and Edge Cases              ║");
        $display("╚════════════════════════════════════════════════════════╝\n");

        // ==================== ARITHMETIC OPERATIONS ====================
        $display("\n┌─ ARITHMETIC OPERATIONS ────────────────────────────────┐");
        
        // Group 1: Transfer and Increment
        $display("\n▶ Transfer and Increment Operations:");
        test_alu(4'b0101, 4'bxxxx, 4'b0000, 1'b0, 4'b0101, 1'b0, "Transfer A");
        test_alu(4'b0101, 4'bxxxx, 4'b0001, 1'b1, 4'b0110, 1'b0, "A + 1");
        test_alu(4'b1111, 4'bxxxx, 4'b0001, 1'b1, 4'b0000, 1'b1, "A + 1 (overflow)");
        test_alu(4'b0000, 4'bxxxx, 4'b0001, 1'b1, 4'b0001, 1'b0, "0 + 1");

        // Group 2: Addition
        $display("\n▶ Addition Operations (A + B):");
        test_alu(4'b0011, 4'b0010, 4'b0010, 1'b0, 4'b0101, 1'b0, "3 + 2 = 5");
        test_alu(4'b1000, 4'b0100, 4'b0010, 1'b0, 4'b1100, 1'b0, "8 + 4 = 12");
        test_alu(4'b1111, 4'b0001, 4'b0010, 1'b0, 4'b0000, 1'b1, "15 + 1 (overflow)");
        test_alu(4'b0111, 4'b1001, 4'b0010, 1'b0, 4'b0000, 1'b1, "7 + 9 (overflow)");
        test_alu(4'b0000, 4'b0000, 4'b0010, 1'b0, 4'b0000, 1'b0, "0 + 0 = 0");
        test_alu(4'b1111, 4'b1111, 4'b0010, 1'b0, 4'b1110, 1'b1, "15 + 15");

        // Group 3: Addition with Carry In
        $display("\n▶ Addition Operations (A + B + 1):");
        test_alu(4'b0010, 4'b0011, 4'b0011, 1'b1, 4'b0110, 1'b0, "2 + 3 + 1 = 6");
        test_alu(4'b1111, 4'b1111, 4'b0011, 1'b1, 4'b1111, 1'b1, "15 + 15 + 1");
        test_alu(4'b1110, 4'b0001, 4'b0011, 1'b1, 4'b0000, 1'b1, "14 + 1 + 1 (overflow)");

        // Group 4: Subtraction (Two's Complement)
        $display("\n▶ Subtraction Operations (A - B using A + ~B):");
        test_alu(4'b0101, 4'b0011, 4'b0100, 1'b0, 4'b0010, 1'b0, "5 - 3 = 2");
        test_alu(4'b1000, 4'b0100, 4'b0100, 1'b0, 4'b0100, 1'b0, "8 - 4 = 4");
        test_alu(4'b0011, 4'b0101, 4'b0100, 1'b0, 4'b1110, 1'b0, "3 - 5 = -2");
        test_alu(4'b0000, 4'b0001, 4'b0100, 1'b0, 4'b1111, 1'b0, "0 - 1 = -1");

        // Group 5: Subtraction (Two's Complement + 1)
        $display("\n▶ Subtraction Operations (A - B using A + ~B + 1):");
        test_alu(4'b1000, 4'b0011, 4'b0101, 1'b1, 4'b0101, 1'b0, "8 - 3 = 5");
        test_alu(4'b1010, 4'b0101, 4'b0101, 1'b1, 4'b0101, 1'b0, "10 - 5 = 5");
        test_alu(4'b0101, 4'b1000, 4'b0101, 1'b1, 4'b1101, 1'b0, "5 - 8 = -3");

        // Group 6: Decrement
        $display("\n▶ Decrement Operation (A - 1):");
        test_alu(4'b0101, 4'bxxxx, 4'b0110, 1'b0, 4'b0100, 1'b0, "5 - 1 = 4");
        test_alu(4'b0001, 4'bxxxx, 4'b0110, 1'b0, 4'b0000, 1'b0, "1 - 1 = 0");
        test_alu(4'b0000, 4'bxxxx, 4'b0110, 1'b0, 4'b1111, 1'b1, "0 - 1 (underflow)");
        test_alu(4'b1000, 4'bxxxx, 4'b0110, 1'b0, 4'b0111, 1'b0, "8 - 1 = 7");

        // ==================== LOGICAL OPERATIONS ====================
        $display("\n\n┌─ LOGICAL OPERATIONS ───────────────────────────────────┐");

        // Group 7: AND
        $display("\n▶ AND Operations:");
        test_alu(4'b1010, 4'b0101, 4'b1001, 1'b0, 4'b0000, 1'b0, "1010 AND 0101 = 0000");
        test_alu(4'b1111, 4'b0101, 4'b1001, 1'b0, 4'b0101, 1'b0, "1111 AND 0101 = 0101");
        test_alu(4'b1111, 4'b1111, 4'b1001, 1'b0, 4'b1111, 1'b0, "1111 AND 1111 = 1111");
        test_alu(4'b0000, 4'b1111, 4'b1001, 1'b0, 4'b0000, 1'b0, "0000 AND 1111 = 0000");

        // Group 8: OR
        $display("\n▶ OR Operations:");
        test_alu(4'b1010, 4'b0101, 4'b1010, 1'b0, 4'b1111, 1'b0, "1010 OR 0101 = 1111");
        test_alu(4'b0000, 4'b0100, 4'b1010, 1'b0, 4'b0100, 1'b0, "0000 OR 0100 = 0100");
        test_alu(4'b1000, 4'b0100, 4'b1010, 1'b0, 4'b1100, 1'b0, "1000 OR 0100 = 1100");
        test_alu(4'b0000, 4'b0000, 4'b1010, 1'b0, 4'b0000, 1'b0, "0000 OR 0000 = 0000");

        // Group 9: XOR
        $display("\n▶ XOR Operations:");
        test_alu(4'b1010, 4'b0101, 4'b1011, 1'b0, 4'b1111, 1'b0, "1010 XOR 0101 = 1111");
        test_alu(4'b1111, 4'b1111, 4'b1011, 1'b0, 4'b0000, 1'b0, "1111 XOR 1111 = 0000");
        test_alu(4'b1010, 4'b1010, 4'b1011, 1'b0, 4'b0000, 1'b0, "1010 XOR 1010 = 0000");
        test_alu(4'b0101, 4'b1010, 4'b1011, 1'b0, 4'b1111, 1'b0, "0101 XOR 1010 = 1111");

        // Group 10: NOT
        $display("\n▶ NOT Operations:");
        test_alu(4'b1010, 4'bxxxx, 4'b1101, 1'b0, 4'b0101, 1'b0, "NOT 1010 = 0101");
        test_alu(4'b0000, 4'bxxxx, 4'b1101, 1'b0, 4'b1111, 1'b0, "NOT 0000 = 1111");
        test_alu(4'b1111, 4'bxxxx, 4'b1101, 1'b0, 4'b0000, 1'b0, "NOT 1111 = 0000");
        test_alu(4'b0001, 4'bxxxx, 4'b1101, 1'b0, 4'b1110, 1'b0, "NOT 0001 = 1110");

        // ==================== SHIFT OPERATIONS ====================
        $display("\n\n┌─ SHIFT OPERATIONS ─────────────────────────────────────┐");

        // Group 11: Shift Right
        $display("\n▶ Shift Right Operations (shift_in_r = a[3]):");
        test_alu(4'b1101, 4'bxxxx, 4'b1000, 1'b0, 4'b1110, 1'b0, "SR: 1101 → 1110");
        test_alu(4'b0101, 4'bxxxx, 4'b1000, 1'b0, 4'b0010, 1'b0, "SR: 0101 → 0010");
        test_alu(4'b1111, 4'bxxxx, 4'b1000, 1'b0, 4'b1111, 1'b0, "SR: 1111 → 1111");
        test_alu(4'b0001, 4'bxxxx, 4'b1000, 1'b0, 4'b0000, 1'b0, "SR: 0001 → 0000");

        // Group 12: Shift Left
        $display("\n▶ Shift Left Operations (shift_in_l = a[0]):");
        test_alu(4'b1101, 4'bxxxx, 4'b1100, 1'b0, 4'b1011, 1'b0, "SL: 1101 → 1011");
        test_alu(4'b0101, 4'bxxxx, 4'b1100, 1'b0, 4'b1010, 1'b0, "SL: 0101 → 1010");
        test_alu(4'b1000, 4'bxxxx, 4'b1100, 1'b0, 4'b0001, 1'b0, "SL: 1000 → 0001");
        test_alu(4'b1111, 4'bxxxx, 4'b1100, 1'b0, 4'b1111, 1'b0, "SL: 1111 → 1111");

        // ==================== EDGE CASES & STRESS TESTS ====================
        $display("\n\n┌─ EDGE CASES & STRESS TESTS ─────────────────────────────┐");

        // Group 13: All zeros and all ones
        $display("\n▶ Boundary Conditions:");
        test_alu(4'b0000, 4'b0000, 4'b0010, 1'b0, 4'b0000, 1'b0, "0 + 0");
        test_alu(4'b1111, 4'b1111, 4'b0010, 1'b0, 4'b1110, 1'b1, "15 + 15");
        test_alu(4'b1111, 4'bxxxx, 4'b0001, 1'b1, 4'b0000, 1'b1, "Max + 1");
        test_alu(4'b0000, 4'bxxxx, 4'b0110, 1'b0, 4'b1111, 1'b1, "Min - 1");

        // Group 14: Single bit operations
        $display("\n▶ Single Bit Operations:");
        test_alu(4'b0001, 4'b0000, 4'b0010, 1'b0, 4'b0001, 1'b0, "1 + 0");
        test_alu(4'b1000, 4'b0000, 4'b0010, 1'b0, 4'b1000, 1'b0, "8 + 0");
        test_alu(4'b0001, 4'b0001, 4'b0010, 1'b0, 4'b0010, 1'b0, "1 + 1");
        test_alu(4'b1000, 4'b1000, 4'b0010, 1'b0, 4'b0000, 1'b1, "8 + 8");

        // Group 15: Carry propagation
        $display("\n▶ Carry Propagation Tests:");
        test_alu(4'b0111, 4'b0001, 4'b0010, 1'b0, 4'b1000, 1'b0, "7 + 1 (no carry)");
        test_alu(4'b1000, 4'b1000, 4'b0010, 1'b0, 4'b0000, 1'b1, "8 + 8 (with carry)");
        test_alu(4'b0111, 4'b1001, 4'b0010, 1'b0, 4'b0000, 1'b1, "7 + 9 (with carry)");

        // Print summary
        print_summary();
        
        $finish;
    end

    // Task: Test ALU operation with verification
    task test_alu(
        input [3:0] in_a, 
        input [3:0] in_b, 
        input [3:0] in_sel, 
        input in_cin,
        input [3:0] exp_result, 
        input exp_carry,
        input string description
    );
    begin
        a = in_a;
        b = in_b;
        select = in_sel;
        cin = in_cin;
        #10;
        
        total_tests = total_tests + 1;
        
        if (result === exp_result && carry === exp_carry) begin
            passed_tests = passed_tests + 1;
            $display("  ✓ PASS | %s", description);
        end else begin
            failed_tests = failed_tests + 1;
            $display("  ✗ FAIL | %s", description);
            $display("          Expected: result=%b (%0d), carry=%b", exp_result, exp_result, exp_carry);
            $display("          Got:      result=%b (%0d), carry=%b", result, result, carry);
        end
    end
    endtask

    // Print test summary
    task print_summary;
    begin
        $display("\n\n┌────────────────────────────────────────────────────────┐");
        $display("║                   TEST SUMMARY                        ║");
        $display("├────────────────────────────────────────────────────────┤");
        $display("║  Total Tests:  %3d                                     ║", total_tests);
        $display("║  Passed:       %3d  ✓                                 ║", passed_tests);
        $display("║  Failed:       %3d  ✗                                 ║", failed_tests);
        if (failed_tests == 0)
            $display("║                                                        ║");
            $display("║              🎉 ALL TESTS PASSED! 🎉                  ║");
        $display("└────────────────────────────────────────────────────────┘\n");
    end
    endtask

endmodule

alu/alu_waves.vcd
$date
	Fri Apr 24 00:52:59 2026
$end
$version
	Icarus Verilog
$end
$timescale
	1ps
$end
$scope module alu_4bit_comprehensive_tb $end
$var wire 4 ! result [3:0] $end
$var wire 1 " carry $end
$var reg 4 # a [3:0] $end
$var reg 4 $ b [3:0] $end
$var reg 1 % cin $end
$var reg 4 & select [3:0] $end
$var integer 32 ' failed_tests [31:0] $end
$var integer 32 ( passed_tests [31:0] $end
$var integer 32 ) total_tests [31:0] $end
$scope module uut $end
$var wire 4 * a [3:0] $end
$var wire 4 + b [3:0] $end
$var wire 1 % cin $end
$var wire 4 , select [3:0] $end
$var reg 1 " carry $end
$var reg 4 - result [3:0] $end
$upscope $end
$scope task print_summary $end
$upscope $end
$scope task test_alu $end
$var reg 1 . exp_carry $end
$var reg 4 / exp_result [3:0] $end
$var reg 4 0 in_a [3:0] $end
$var reg 4 1 in_b [3:0] $end
$var reg 1 2 in_cin $end
$var reg 4 3 in_sel [3:0] $end
$upscope $end
$upscope $end
$enddefinitions $end
$comment Show the parameter values. $end
$dumpall
$end
#0
$dumpvars
b0 3
02
bx 1
b101 0
b101 /
0.
b101 -
b0 ,
bx +
b101 *
b0 )
b0 (
b0 '
b0 &
0%
bx $
b101 #
0"
b101 !
$end
#10000
b110 !
b110 -
1%
b1 &
b1 ,
b110 /
12
b1 3
b1 (
b1 )
#20000
1"
b0 !
b0 -
b1111 #
b1111 *
1.
b0 /
b1111 0
b10 (
b10 )
#30000
b1 !
b1 -
0"
b0 #
b0 *
0.
b1 /
b0 0
b11 (
b11 )
#40000
b101 !
b101 -
0%
b10 &
b10 ,
b10 $
b10 +
b11 #
b11 *
b101 /
02
b10 3
b10 1
b11 0
b100 (
b100 )
#50000
b1100 !
b1100 -
b100 $
b100 +
b1000 #
b1000 *
b1100 /
b100 1
b1000 0
b101 (
b101 )
#60000
1"
b0 !
b0 -
b1 $
b1 +
b1111 #
b1111 *
1.
b0 /
b1 1
b1111 0
b110 (
b110 )
#70000
1"
b1001 $
b1001 +
b111 #
b111 *
b1001 1
b111 0
b111 (
b111 )
#80000
0"
b0 $
b0 +
b0 #
b0 *
0.
b0 1
b0 0
b1000 (
b1000 )
#90000
1"
b1110 !
b1110 -
b1111 $
b1111 +
b1111 #
b1111 *
1.
b1110 /
b1111 1
b1111 0
b1001 (
b1001 )
#100000
0"
b110 !
b110 -
1%
b11 &
b11 ,
b11 $
b11 +
b10 #
b10 *
0.
b110 /
12
b11 3
b11 1
b10 0
b1010 (
b1010 )
#110000
1"
b1111 !
b1111 -
b1111 $
b1111 +
b1111 #
b1111 *
1.
b1111 /
b1111 1
b1111 0
b1011 (
b1011 )
#120000
1"
b0 !
b0 -
b1 $
b1 +
b1110 #
b1110 *
b0 /
b1 1
b1110 0
b1100 (
b1100 )
#130000
b10 !
b10 -
0"
0%
b100 &
b100 ,
b11 $
b11 +
b101 #
b101 *
0.
b10 /
02
b100 3
b11 1
b101 0
b1101 (
b1101 )
#140000
b100 !
b100 -
b100 $
b100 +
b1000 #
b1000 *
b100 /
b100 1
b1000 0
b1110 (
b1110 )
#150000
b1110 !
b1110 -
b101 $
b101 +
b11 #
b11 *
b1110 /
b101 1
b11 0
b1111 (
b1111 )
#160000
b1111 !
b1111 -
b1 $
b1 +
b0 #
b0 *
b1111 /
b1 1
b0 0
b10000 (
b10000 )
#170000
b101 !
b101 -
1%
b101 &
b101 ,
b11 $
b11 +
b1000 #
b1000 *
b101 /
12
b101 3
b11 1
b1000 0
b10001 (
b10001 )
#180000
b101 !
b101 -
b101 $
b101 +
b1010 #
b1010 *
b101 1
b1010 0
b10010 (
b10010 )
#190000
b1101 !
b1101 -
b1000 $
b1000 +
b101 #
b101 *
b1101 /
b1000 1
b101 0
b10011 (
b10011 )
#200000
b100 !
b100 -
0%
b110 &
b110 ,
bx $
bx +
b100 /
02
b110 3
bx 1
b10100 (
b10100 )
#210000
b0 !
b0 -
b1 #
b1 *
b0 /
b1 0
b10101 (
b10101 )
#220000
1"
b1111 !
b1111 -
b0 #
b0 *
1.
b1111 /
b0 0
b10110 (
b10110 )
#230000
0"
b111 !
b111 -
b1000 #
b1000 *
0.
b111 /
b1000 0
b10111 (
b10111 )
#240000
b0 !
b0 -
b1001 &
b1001 ,
b101 $
b101 +
b1010 #
b1010 *
b0 /
b1001 3
b101 1
b1010 0
b11000 (
b11000 )
#250000
b101 !
b101 -
b1111 #
b1111 *
b101 /
b1111 0
b11001 (
b11001 )
#260000
b1111 !
b1111 -
b1111 $
b1111 +
b1111 /
b1111 1
b11010 (
b11010 )
#270000
b0 !
b0 -
b0 #
b0 *
b0 /
b0 0
b11011 (
b11011 )
#280000
b1111 !
b1111 -
b1010 &
b1010 ,
b101 $
b101 +
b1010 #
b1010 *
b1111 /
b1010 3
b101 1
b1010 0
b11100 (
b11100 )
#290000
b100 !
b100 -
b100 $
b100 +
b0 #
b0 *
b100 /
b100 1
b0 0
b11101 (
b11101 )
#300000
b1100 !
b1100 -
b1000 #
b1000 *
b1100 /
b1000 0
b11110 (
b11110 )
#310000
b0 !
b0 -
b0 $
b0 +
b0 #
b0 *
b0 /
b0 1
b0 0
b11111 (
b11111 )
#320000
b1111 !
b1111 -
b1011 &
b1011 ,
b101 $
b101 +
b1010 #
b1010 *
b1111 /
b1011 3
b101 1
b1010 0
b100000 (
b100000 )
#330000
b0 !
b0 -
b1111 $
b1111 +
b1111 #
b1111 *
b0 /
b1111 1
b1111 0
b100001 (
b100001 )
#340000
b1010 $
b1010 +
b1010 #
b1010 *
b1010 1
b1010 0
b100010 (
b100010 )
#350000
b1111 !
b1111 -
b101 #
b101 *
b1111 /
b101 0
b100011 (
b100011 )
#360000
b101 !
b101 -
b1101 &
b1101 ,
bx $
bx +
b1010 #
b1010 *
b101 /
b1101 3
bx 1
b1010 0
b100100 (
b100100 )
#370000
b1111 !
b1111 -
b0 #
b0 *
b1111 /
b0 0
b100101 (
b100101 )
#380000
b0 !
b0 -
b1111 #
b1111 *
b0 /
b1111 0
b100110 (
b100110 )
#390000
b1110 !
b1110 -
b1 #
b1 *
b1110 /
b1 0
b100111 (
b100111 )
#400000
b1110 !
b1110 -
b1000 &
b1000 ,
b1101 #
b1101 *
b1000 3
b1101 0
b101000 (
b101000 )
#410000
b10 !
b10 -
b101 #
b101 *
b10 /
b101 0
b101001 (
b101001 )
#420000
b1111 !
b1111 -
b1111 #
b1111 *
b1111 /
b1111 0
b101010 (
b101010 )
#430000
b0 !
b0 -
b1 #
b1 *
b0 /
b1 0
b101011 (
b101011 )
#440000
b1011 !
b1011 -
b1100 &
b1100 ,
b1101 #
b1101 *
b1011 /
b1100 3
b1101 0
b101100 (
b101100 )
#450000
b1010 !
b1010 -
b101 #
b101 *
b1010 /
b101 0
b101101 (
b101101 )
#460000
b1 !
b1 -
b1000 #
b1000 *
b1 /
b1000 0
b101110 (
b101110 )
#470000
b1111 !
b1111 -
b1111 #
b1111 *
b1111 /
b1111 0
b101111 (
b101111 )
#480000
b0 !
b0 -
b10 &
b10 ,
b0 $
b0 +
b0 #
b0 *
b0 /
b10 3
b0 1
b0 0
b110000 (
b110000 )
#490000
1"
b1110 !
b1110 -
b1111 $
b1111 +
b1111 #
b1111 *
1.
b1110 /
b1111 1
b1111 0
b110001 (
b110001 )
#500000
1"
b0 !
b0 -
1%
b1 &
b1 ,
bx $
bx +
b0 /
12
b1 3
bx 1
b110010 (
b110010 )
#510000
b1111 !
b1111 -
1"
0%
b110 &
b110 ,
b0 #
b0 *
b1111 /
02
b110 3
b0 0
b110011 (
b110011 )
#520000
0"
b1 !
b1 -
b10 &
b10 ,
b0 $
b0 +
b1 #
b1 *
0.
b1 /
b10 3
b0 1
b1 0
b110100 (
b110100 )
#530000
b1000 !
b1000 -
b1000 #
b1000 *
b1000 /
b1000 0
b110101 (
b110101 )
#540000
b10 !
b10 -
b1 $
b1 +
b1 #
b1 *
b10 /
b1 1
b1 0
b110110 (
b110110 )
#550000
1"
b0 !
b0 -
b1000 $
b1000 +
b1000 #
b1000 *
1.
b0 /
b1000 1
b1000 0
b110111 (
b110111 )
#560000
b1000 !
b1000 -
0"
b1 $
b1 +
b111 #
b111 *
0.
b1000 /
b1 1
b111 0
b111000 (
b111000 )
#570000
1"
b0 !
b0 -
b1000 $
b1000 +
b1000 #
b1000 *
1.
b0 /
b1000 1
b1000 0
b111001 (
b111001 )
#580000
1"
b1001 $
b1001 +
b111 #
b111 *
b1001 1
b111 0
b111010 (
b111010 )
#590000
b111011 (
b111011 )
