alu/alu.v
// 4-bit ALU
// op: 3-bit operation select
//  000 -> ADD  (a + b)
//  001 -> SUB  (a - b)
//  010 -> AND  (a & b)
//  011 -> OR   (a | b)
//  100 -> XOR  (a ^ b)
//  101 -> NOT  (~a)
//  110 -> NAND (~(a & b))
//  111 -> NOR  (~(a | b))
module alu_4bit (
    input  [3:0] a,      // Operand A
    input  [3:0] b,      // Operand B
    input  [2:0] op,     // Operation select
    output reg [3:0] result,  // Result
    output reg zero,          // Zero flag
    output reg carry          // Carry/borrow flag
);
    reg [4:0] temp;

    always @(*) begin
        carry = 1'b0;
        case (op)
            3'b000: begin temp = {1'b0, a} + {1'b0, b}; result = temp[3:0]; carry = temp[4]; end  // ADD
            3'b001: begin temp = {1'b0, a} - {1'b0, b}; result = temp[3:0]; carry = temp[4]; end  // SUB
            3'b010: begin result = a & b; end   // AND
            3'b011: begin result = a | b; end   // OR
            3'b100: begin result = a ^ b; end   // XOR
            3'b101: begin result = ~a;   end    // NOT
            3'b110: begin result = ~(a & b); end // NAND
            3'b111: begin result = ~(a | b); end // NOR
            default: result = 4'b0000;
        endcase
        zero = (result == 4'b0000) ? 1'b1 : 1'b0;
    end

endmodule

alu/alu_tb.v
`timescale 1ns / 1ps

module alu_4bit_tb;

    reg  [3:0] a, b;
    reg  [2:0] op;
    wire [3:0] result;
    wire       zero, carry;

    // Instantiate DUT
    alu_4bit uut (
        .a(a),
        .b(b),
        .op(op),
        .result(result),
        .zero(zero),
        .carry(carry)
    );

    initial begin
        $dumpfile("alu_waves.vcd");
        $dumpvars(0, alu_4bit_tb);

        a = 4'b0101; b = 4'b0011;

        // ADD: 5+3=8
        op = 3'b000; #10;
        $display("t=%0t | op=ADD  a=%b b=%b | result=%b carry=%b zero=%b", $time, a, b, result, carry, zero);

        // SUB: 5-3=2
        op = 3'b001; #10;
        $display("t=%0t | op=SUB  a=%b b=%b | result=%b carry=%b zero=%b", $time, a, b, result, carry, zero);

        // AND: 5&3=1
        op = 3'b010; #10;
        $display("t=%0t | op=AND  a=%b b=%b | result=%b zero=%b", $time, a, b, result, zero);

        // OR: 5|3=7
        op = 3'b011; #10;
        $display("t=%0t | op=OR   a=%b b=%b | result=%b zero=%b", $time, a, b, result, zero);

        // XOR: 5^3=6
        op = 3'b100; #10;
        $display("t=%0t | op=XOR  a=%b b=%b | result=%b zero=%b", $time, a, b, result, zero);

        // NOT: ~5=10
        op = 3'b101; #10;
        $display("t=%0t | op=NOT  a=%b     | result=%b zero=%b", $time, a, result, zero);

        // NAND
        op = 3'b110; #10;
        $display("t=%0t | op=NAND a=%b b=%b | result=%b zero=%b", $time, a, b, result, zero);

        // NOR
        op = 3'b111; #10;
        $display("t=%0t | op=NOR  a=%b b=%b | result=%b zero=%b", $time, a, b, result, zero);

        // Test zero flag: ADD 0+0=0
        a = 4'b0000; b = 4'b0000; op = 3'b000; #10;
        $display("t=%0t | op=ADD  a=%b b=%b | result=%b zero=%b (zero flag)", $time, a, b, result, zero);

        // Test carry: ADD 15+1 = overflow
        a = 4'b1111; b = 4'b0001; op = 3'b000; #10;
        $display("t=%0t | op=ADD  a=%b b=%b | result=%b carry=%b (carry flag)", $time, a, b, result, carry);

        #10;
        $finish;
    end

endmodule

alu/alu_waves.vcd
$date
	Fri Apr 17 11:19:03 2026
$end
$version
	Icarus Verilog
$end
$timescale
	1ps
$end
$scope module alu_4bit_tb $end
$var wire 1 ! zero $end
$var wire 4 " result [3:0] $end
$var wire 1 # carry $end
$var reg 4 $ a [3:0] $end
$var reg 4 % b [3:0] $end
$var reg 3 & op [2:0] $end
$scope module uut $end
$var wire 4 ' a [3:0] $end
$var wire 4 ( b [3:0] $end
$var wire 3 ) op [2:0] $end
$var reg 1 # carry $end
$var reg 4 * result [3:0] $end
$var reg 5 + temp [4:0] $end
$var reg 1 ! zero $end
$upscope $end
$upscope $end
$enddefinitions $end
$comment Show the parameter values. $end
$dumpall
$end
#0
$dumpvars
b1000 +
b1000 *
b0 )
b11 (
b101 '
b0 &
b11 %
b101 $
0#
b1000 "
0!
$end
#10000
b10 "
b10 *
b10 +
b1 &
b1 )
#20000
b1 "
b1 *
b10 &
b10 )
#30000
b111 "
b111 *
b11 &
b11 )
#40000
b110 "
b110 *
b100 &
b100 )
#50000
b1010 "
b1010 *
b101 &
b101 )
#60000
b1110 "
b1110 *
b110 &
b110 )
#70000
b1000 "
b1000 *
b111 &
b111 )
#80000
1!
b0 "
b0 *
b0 +
b0 &
b0 )
b0 %
b0 (
b0 $
b0 '
#90000
1#
b10000 +
b1 %
b1 (
b1111 $
b1111 '
