graycoder_bcd/gtob.v
module bcd_to_gray(
    input [3:0] bcd,
    output [3:0] gray
);

    wire [3:0] binary;
    
    assign binary = bcd;
    assign gray = binary ^ (binary >> 1);

endmodule

graycoder_bcd/gtob_tb.v
module bcd_to_gray_tb;

  // Parameters

  //Ports
  reg [3:0] bcd;
  wire [3:0] gray;

  bcd_to_gray  bcd_to_gray_inst (
    .bcd(bcd),
    .gray(gray)
  );

    initial begin
        // Waveform Dumping
        $dumpfile("bcd_to_gray_waves.vcd");
        $dumpvars(0, bcd_to_gray_tb);

        // Test Cases
        bcd = 4'b0000; #10; // 0
        bcd = 4'b0001; #10; // 1
        bcd = 4'b0010; #10; // 2
        bcd = 4'b0011; #10; // 3
        bcd = 4'b0100; #10; // 4
        bcd = 4'b0101; #10; // 5
        bcd = 4'b0110; #10; // 6
        bcd = 4'b0111; #10; // 7
        bcd = 4'b1000; #10; // 8
        bcd = 4'b1001; #10; // 9

        $finish; // End simulation
    end

endmodule

graycoder_bcd/bcd_to_gray_waves.vcd
$date
	Thu Feb  5 11:16:03 2026
$end
$version
	Icarus Verilog
$end
$timescale
	1s
$end
$scope module bcd_to_gray_tb $end
$var wire 4 ! gray [3:0] $end
$var reg 4 " bcd [3:0] $end
$scope module bcd_to_gray_inst $end
$var wire 4 # bcd [3:0] $end
$var wire 4 $ binary [3:0] $end
$var wire 4 % gray [3:0] $end
$upscope $end
$upscope $end
$enddefinitions $end
#0
$dumpvars
b0 %
b0 $
b0 #
b0 "
b0 !
$end
#10
b1 !
b1 %
b1 $
b1 "
b1 #
#20
b11 !
b11 %
b10 $
b10 "
b10 #
#30
b10 !
b10 %
b11 $
b11 "
b11 #
#40
b110 !
b110 %
b100 $
b100 "
b100 #
#50
b111 !
b111 %
b101 $
b101 "
b101 #
#60
b101 !
b101 %
b110 $
b110 "
b110 #
#70
b100 !
b100 %
b111 $
b111 "
b111 #
#80
b1100 !
b1100 %
b1000 $
b1000 "
b1000 #
#90
b1101 !
b1101 %
b1001 $
b1001 "
b1001 #
